{
  "savedAt": "2026-03-01T04:35:00.515Z",
  "id": "hashnote-usyc",
  "detail": {
    "id": "hashnote-usyc",
    "symbol": "usyc",
    "name": "Circle USYC",
    "web_slug": "hashnote-usyc",
    "asset_platform_id": "ethereum",
    "platforms": {
      "ethereum": "0x136471a34f6ef19fe571effc1ca711fdb8e49f2b",
      "binance-smart-chain": "0x8d0fa28f221eb5735bc71d3a0da67ee5bc821311",
      "solana": "7LWanZteUKtvFjv4MHYgKXXdAuCQYFPJysL9pxxdRQGn"
    },
    "detail_platforms": {
      "ethereum": {
        "decimal_place": 6,
        "contract_address": "0x136471a34f6ef19fe571effc1ca711fdb8e49f2b",
        "geckoterminal_url": "https://www.geckoterminal.com/eth/tokens/0x136471a34f6ef19fe571effc1ca711fdb8e49f2b"
      },
      "binance-smart-chain": {
        "decimal_place": 6,
        "contract_address": "0x8d0fa28f221eb5735bc71d3a0da67ee5bc821311",
        "geckoterminal_url": "https://www.geckoterminal.com/bsc/tokens/0x8d0fa28f221eb5735bc71d3a0da67ee5bc821311"
      },
      "solana": {
        "decimal_place": 6,
        "contract_address": "7LWanZteUKtvFjv4MHYgKXXdAuCQYFPJysL9pxxdRQGn",
        "geckoterminal_url": "https://www.geckoterminal.com/solana/tokens/7LWanZteUKtvFjv4MHYgKXXdAuCQYFPJysL9pxxdRQGn"
      }
    },
    "block_time_in_minutes": 0,
    "hashing_algorithm": null,
    "categories": [
      "Tokenized Assets",
      "BNB Chain Ecosystem",
      "Solana Ecosystem",
      "Ethereum Ecosystem",
      "Real World Assets (RWA)",
      "Tokenized Treasury Bills (T-Bills)"
    ],
    "preview_listing": false,
    "public_notice": null,
    "additional_notices": [],
    "description": {
      "en": "USYC: Tokenized Money Market Fund\r\n\r\nHashnote International Short Duration Yield Fund Ltd. invests in short-term U.S. Treasury Bills and performs repo/reverse repo activities as the underlying asset of the USYC token.\r\n\r\nUSYC earns short-term Fed rate returns. Tokenization enables the fund to deliver rapid transactions, onchain transparency, and seamless composability—while maintaining strong controls across regulatory and credit dimensions.\r\n"
    },
    "links": {
      "homepage": [
        "https://usyc.hashnote.com/",
        "https://www.circle.com/"
      ],
      "whitepaper": "https://developers.circle.com/tokenized/usyc/overview?_gl=1*1tinvsh*_gcl_au*MTc2OTc4MTMzNC4xNzcxOTYwMzk0*_ga*MTA4NzQzMjI0MS4xNzcxOTYwMzk0*_ga_GJDVPCQNRV*czE3NzE5NjAzOTIkbzEkZzEkdDE3NzE5NjA0NDkkajQ2JGwwJGgw",
      "blockchain_site": [
        "https://etherscan.io/token/0x136471a34f6ef19fe571effc1ca711fdb8e49f2b",
        "https://intel.arkm.com/explorer/token/hashnote-usyc ",
        "https://ethplorer.io/address/0x136471a34f6ef19fE571EFFC1CA711fdb8E49f2b",
        "https://bscscan.com/token/0x8D0fA28f221eB5735BC71d3a0Da67EE5bC821311",
        "https://binplorer.com/address/0x8D0fA28f221eB5735BC71d3a0Da67EE5bC821311",
        "https://solscan.io/token/7LWanZteUKtvFjv4MHYgKXXdAuCQYFPJysL9pxxdRQGn",
        "https://intel.arkm.com/explorer/token/hashnote-usyc"
      ],
      "official_forum_url": [],
      "chat_url": [],
      "announcement_url": [],
      "snapshot_url": null,
      "twitter_screen_name": "Hashnote_Labs",
      "facebook_username": "",
      "bitcointalk_thread_identifier": null,
      "telegram_channel_identifier": "",
      "subreddit_url": null,
      "repos_url": {
        "github": [],
        "bitbucket": []
      }
    },
    "image": {
      "thumb": "https://coin-images.coingecko.com/coins/images/51054/thumb/Hashnote_SDYC_200x200.png?1730370965",
      "small": "https://coin-images.coingecko.com/coins/images/51054/small/Hashnote_SDYC_200x200.png?1730370965",
      "large": "https://coin-images.coingecko.com/coins/images/51054/large/Hashnote_SDYC_200x200.png?1730370965"
    },
    "country_origin": "",
    "genesis_date": null,
    "contract_address": "0x136471a34f6ef19fe571effc1ca711fdb8e49f2b",
    "sentiment_votes_up_percentage": 0,
    "sentiment_votes_down_percentage": 100,
    "watchlist_portfolio_users": 745,
    "market_cap_rank": 42,
    "market_cap_rank_with_rehypothecated": 53,
    "market_data": {
      "current_price": {
        "aed": 4.1,
        "ars": 1560.31,
        "aud": 1.57,
        "bch": 0.00251357,
        "bdt": 136.26,
        "bhd": 0.420084,
        "bmd": 1.12,
        "bnb": 0.00183325,
        "brl": 5.73,
        "btc": 0.000017,
        "cad": 1.52,
        "chf": 0.859246,
        "clp": 975.79,
        "cny": 7.66,
        "czk": 22.92,
        "dkk": 7.06,
        "dot": 0.7081635,
        "eos": 14.21406,
        "eth": 0.00057994,
        "eur": 0.945084,
        "gbp": 0.828377,
        "gel": 2.98,
        "hkd": 8.74,
        "huf": 356.04,
        "idr": 18766.66,
        "ils": 3.5,
        "inr": 101.72,
        "jpy": 174.29,
        "krw": 1608.11,
        "kwd": 0.342375,
        "lkr": 344.84,
        "ltc": 0.02080525,
        "mmk": 2345.38,
        "mxn": 19.25,
        "myr": 4.35,
        "ngn": 1515.53,
        "nok": 10.62,
        "nzd": 1.86,
        "php": 64.49,
        "pkr": 311.67,
        "pln": 3.99,
        "rub": 86.09,
        "sar": 4.19,
        "sek": 10.09,
        "sgd": 1.41,
        "sol": 0.01367459,
        "thb": 34.53,
        "try": 49.05,
        "twd": 35.06,
        "uah": 48.13,
        "usd": 1.12,
        "vef": 0.111835,
        "vnd": 29090,
        "xag": 0.01453891,
        "xau": 0.00021161,
        "xdr": 0.770901,
        "xlm": 7.264537,
        "xrp": 0.83477529,
        "yfi": 0.00043005,
        "zar": 17.79,
        "bits": 17,
        "link": 0.13027629,
        "sats": 1699.5
      },
      "total_value_locked": null,
      "mcap_to_tvl_ratio": null,
      "fdv_to_tvl_ratio": null,
      "roi": null,
      "ath": {
        "aed": 4.11,
        "ars": 1633.99,
        "aud": 1.83,
        "bch": 0.00427331,
        "bdt": 137.01,
        "bhd": 0.421621,
        "bmd": 1.12,
        "bnb": 0.00211078,
        "brl": 7.32,
        "btc": 0.00001842,
        "cad": 1.62,
        "chf": 0.998515,
        "clp": 1104.01,
        "cny": 8.13,
        "czk": 26.78,
        "dkk": 7.93,
        "dot": 0.96804072,
        "eos": 15.573876,
        "eth": 0.00077387,
        "eur": 1.063,
        "gbp": 0.891509,
        "gel": 3.13,
        "hkd": 8.75,
        "huf": 439.25,
        "idr": 18834.51,
        "ils": 4.21,
        "inr": 102.4,
        "jpy": 176.6,
        "krw": 1647.58,
        "kwd": 0.34467,
        "lkr": 346.73,
        "ltc": 0.02378208,
        "mmk": 2348.08,
        "mxn": 23.2,
        "myr": 4.99,
        "ngn": 1832.88,
        "nok": 12.59,
        "nzd": 1.99,
        "php": 66.35,
        "pkr": 318.44,
        "pln": 4.54,
        "rub": 124.48,
        "sar": 4.19,
        "sek": 12.21,
        "sgd": 1.5,
        "sol": 0.01574501,
        "thb": 38.48,
        "try": 49.16,
        "twd": 36.7,
        "uah": 48.38,
        "usd": 1.12,
        "vef": 0.111964,
        "vnd": 29275,
        "xag": 0.03805031,
        "xau": 0.00042277,
        "xdr": 0.853137,
        "xlm": 11.931138,
        "xrp": 2.158344,
        "yfi": 0.00046724,
        "zar": 21.6,
        "bits": 18.42,
        "link": 0.1506537,
        "sats": 1842.35
      },
      "ath_change_percentage": {
        "aed": -0.12053,
        "ars": -4.50905,
        "aud": -14.40201,
        "bch": -41.17976,
        "bdt": -0.54588,
        "bhd": -0.36442,
        "bmd": -0.11521,
        "bnb": -13.14815,
        "brl": -21.71224,
        "btc": -7.75366,
        "cad": -5.86899,
        "chf": -13.94763,
        "clp": -11.61424,
        "cny": -5.77604,
        "czk": -14.4367,
        "dkk": -10.93211,
        "dot": -26.84569,
        "eos": -8.73139,
        "eth": -25.05968,
        "eur": -11.09311,
        "gbp": -7.08145,
        "gel": -4.57303,
        "hkd": -0.13251,
        "huf": -18.94253,
        "idr": -0.36023,
        "ils": -16.87576,
        "inr": -0.65616,
        "jpy": -1.3105,
        "krw": -2.39527,
        "kwd": -0.66597,
        "lkr": -0.54746,
        "ltc": -12.51711,
        "mmk": -0.11521,
        "mxn": -17.03255,
        "myr": -12.87192,
        "ngn": -17.31402,
        "nok": -15.62851,
        "nzd": -6.24101,
        "php": -2.8091,
        "pkr": -2.12636,
        "pln": -11.99543,
        "rub": -30.83461,
        "sar": -0.19385,
        "sek": -17.41925,
        "sgd": -5.72655,
        "sol": -13.1497,
        "thb": -10.25656,
        "try": -0.20701,
        "twd": -4.4602,
        "uah": -0.50346,
        "usd": -0.11521,
        "vef": -0.11521,
        "vnd": -0.63162,
        "xag": -61.79029,
        "xau": -49.94758,
        "xdr": -9.63926,
        "xlm": -39.11279,
        "xrp": -61.32335,
        "yfi": -7.96091,
        "zar": -17.63602,
        "bits": -7.75366,
        "link": -13.526,
        "sats": -7.75366
      },
      "ath_date": {
        "aed": "2026-02-26T17:36:33.149Z",
        "ars": "2026-01-10T17:51:55.112Z",
        "aud": "2025-04-07T14:01:03.151Z",
        "bch": "2025-04-07T07:05:51.034Z",
        "bdt": "2026-02-02T09:43:01.681Z",
        "bhd": "2026-02-26T15:43:04.291Z",
        "bmd": "2026-02-27T11:02:34.368Z",
        "bnb": "2025-03-11T00:56:35.835Z",
        "brl": "2024-12-26T00:21:09.988Z",
        "btc": "2026-02-06T00:22:38.236Z",
        "cad": "2025-03-04T19:26:50.778Z",
        "chf": "2025-01-10T15:51:18.184Z",
        "clp": "2025-01-21T16:20:47.162Z",
        "cny": "2025-04-07T14:01:03.151Z",
        "czk": "2025-02-03T15:20:34.038Z",
        "dkk": "2025-01-10T15:51:18.184Z",
        "dot": "2026-02-06T00:22:38.236Z",
        "eos": "2026-02-06T00:31:42.171Z",
        "eth": "2025-04-09T01:31:43.291Z",
        "eur": "2025-01-10T15:51:18.184Z",
        "gbp": "2025-01-20T02:21:27.445Z",
        "gel": "2025-01-30T15:15:40.736Z",
        "hkd": "2026-02-27T10:56:31.855Z",
        "huf": "2025-01-10T15:51:18.184Z",
        "idr": "2026-02-06T03:02:11.506Z",
        "ils": "2025-04-07T14:01:03.151Z",
        "inr": "2026-01-30T13:28:05.498Z",
        "jpy": "2026-01-14T21:00:41.069Z",
        "krw": "2025-12-23T14:30:22.598Z",
        "kwd": "2025-03-04T19:26:50.778Z",
        "lkr": "2026-02-02T09:48:21.341Z",
        "ltc": "2026-02-06T00:26:49.663Z",
        "mmk": "2026-02-27T11:02:34.368Z",
        "mxn": "2025-03-04T19:26:50.778Z",
        "myr": "2025-03-04T19:26:50.778Z",
        "ngn": "2024-11-27T15:56:11.284Z",
        "nok": "2024-12-20T13:50:59.534Z",
        "nzd": "2025-04-07T14:01:03.151Z",
        "php": "2026-01-14T15:30:38.622Z",
        "pkr": "2025-03-11T01:36:48.747Z",
        "pln": "2025-01-10T15:51:18.184Z",
        "rub": "2025-01-01T21:25:50.957Z",
        "sar": "2026-02-27T11:02:34.368Z",
        "sek": "2025-01-10T15:51:18.184Z",
        "sgd": "2025-04-07T14:01:03.151Z",
        "sol": "2026-02-06T00:26:49.663Z",
        "thb": "2025-04-07T14:01:03.151Z",
        "try": "2026-02-27T11:02:34.368Z",
        "twd": "2025-04-07T14:01:03.151Z",
        "uah": "2026-01-15T23:42:17.317Z",
        "usd": "2026-02-27T11:02:34.368Z",
        "vef": "2026-02-27T11:02:34.368Z",
        "vnd": "2025-12-10T02:26:33.950Z",
        "xag": "2025-04-07T00:21:30.162Z",
        "xau": "2024-12-20T13:50:59.534Z",
        "xdr": "2025-03-04T19:26:50.778Z",
        "xlm": "2024-11-03T18:55:38.260Z",
        "xrp": "2024-11-03T18:55:38.260Z",
        "yfi": "2026-02-06T00:22:38.236Z",
        "zar": "2025-04-07T14:01:03.151Z",
        "bits": "2026-02-06T00:22:38.236Z",
        "link": "2026-02-06T00:22:38.236Z",
        "sats": "2026-02-06T00:22:38.236Z"
      },
      "atl": {
        "aed": 3.77,
        "ars": 1038.31,
        "aud": 1.57,
        "bch": 0.00167376,
        "bdt": 122.7,
        "bhd": 0.386817,
        "bmd": 1.026,
        "bnb": 0.00080455,
        "brl": 5.72,
        "btc": 0.00000879,
        "cad": 1.44,
        "chf": 0.853343,
        "clp": 950.93,
        "cny": 7.45,
        "czk": 22.6,
        "dkk": 6.9,
        "dot": 0.0937642,
        "eos": 0.71679307,
        "eth": 0.00022511,
        "eur": 0.924902,
        "gbp": 0.792163,
        "gel": 2.84,
        "hkd": 7.99,
        "huf": 352.47,
        "idr": 16259.78,
        "ils": 3.43,
        "inr": 86.89,
        "jpy": 152.33,
        "krw": 1449,
        "kwd": 0.315375,
        "lkr": 298.08,
        "ltc": 0.0073231,
        "mmk": 2152.76,
        "mxn": 19.16,
        "myr": 4.34,
        "ngn": 1506.89,
        "nok": 10.6,
        "nzd": 1.74,
        "php": 59.29,
        "pkr": 285.23,
        "pln": 3.92,
        "rub": 80.92,
        "sar": 3.85,
        "sek": 9.8,
        "sgd": 1.37,
        "sol": 0.00442089,
        "thb": 34.48,
        "try": 35.67,
        "twd": 31.39,
        "uah": 42.69,
        "usd": 1.026,
        "vef": 0.102744,
        "vnd": 25811,
        "xag": 0.00977306,
        "xau": 0.00021153,
        "xdr": 0.756675,
        "xlm": 1.815616,
        "xrp": 0.29957093,
        "yfi": 0.00007338,
        "zar": 17.68,
        "bits": 8.79,
        "link": 0.03485819,
        "sats": 878.64
      },
      "atl_change_percentage": {
        "aed": 8.83394,
        "ars": 50.27357,
        "aud": 0.21496,
        "bch": 50.17569,
        "bdt": 11.05159,
        "bhd": 8.60015,
        "bmd": 8.84876,
        "bnb": 127.86041,
        "brl": 0.17582,
        "btc": 93.42418,
        "cad": 5.94093,
        "chf": 0.69169,
        "clp": 2.61394,
        "cny": 2.82176,
        "czk": 1.40337,
        "dkk": 2.35594,
        "dot": 655.25999,
        "eos": 1883.00749,
        "eth": 157.62638,
        "eur": 2.18212,
        "gbp": 4.57155,
        "gel": 5.07917,
        "hkd": 9.41801,
        "huf": 1.01279,
        "idr": 15.41768,
        "ils": 2.10223,
        "inr": 17.07084,
        "jpy": 14.41507,
        "krw": 10.98108,
        "kwd": 8.56119,
        "lkr": 15.68591,
        "ltc": 184.10436,
        "mmk": 8.94734,
        "mxn": 0.44226,
        "myr": 0.14619,
        "ngn": 0.57393,
        "nok": 0.16519,
        "nzd": 6.86109,
        "php": 8.76399,
        "pkr": 9.26821,
        "pln": 1.87185,
        "rub": 6.39095,
        "sar": 8.59473,
        "sek": 2.92501,
        "sgd": 2.7256,
        "sol": 209.3175,
        "thb": 0.15802,
        "try": 37.50915,
        "twd": 11.68994,
        "uah": 12.74265,
        "usd": 8.84876,
        "vef": 8.84876,
        "vnd": 12.70332,
        "xag": 48.76519,
        "xau": 0.03624,
        "xdr": 1.8801,
        "xlm": 300.11424,
        "xrp": 178.65698,
        "yfi": 486.08977,
        "zar": 0.6422,
        "bits": 93.42418,
        "link": 273.73226,
        "sats": 93.42418
      },
      "atl_date": {
        "aed": "2024-12-05T22:31:20.475Z",
        "ars": "2024-11-13T19:22:29.686Z",
        "aud": "2026-02-27T15:41:48.990Z",
        "bch": "2024-12-06T18:15:50.049Z",
        "bdt": "2024-12-05T22:31:20.475Z",
        "bhd": "2024-12-05T22:31:20.475Z",
        "bmd": "2024-12-05T22:31:20.475Z",
        "bnb": "2025-10-13T08:58:12.536Z",
        "brl": "2026-02-27T20:36:43.239Z",
        "btc": "2025-10-05T04:53:20.197Z",
        "cad": "2024-12-05T22:31:20.475Z",
        "chf": "2026-01-30T12:18:28.920Z",
        "clp": "2026-02-09T21:52:26.580Z",
        "cny": "2024-12-05T22:31:20.475Z",
        "czk": "2025-09-23T13:08:42.971Z",
        "dkk": "2025-07-02T17:17:21.461Z",
        "dot": "2024-12-04T14:01:11.387Z",
        "eos": "2024-12-05T16:36:22.584Z",
        "eth": "2025-08-22T21:28:46.060Z",
        "eur": "2025-07-03T10:52:18.999Z",
        "gbp": "2025-06-26T16:42:33.726Z",
        "gel": "2024-11-12T02:56:07.243Z",
        "hkd": "2024-12-05T22:31:20.475Z",
        "huf": "2026-02-09T21:46:25.410Z",
        "idr": "2024-12-05T22:31:20.475Z",
        "ils": "2026-02-04T02:48:08.740Z",
        "inr": "2024-12-05T22:31:20.475Z",
        "jpy": "2025-04-17T14:30:41.929Z",
        "krw": "2024-10-31T14:06:00.565Z",
        "kwd": "2024-12-05T22:31:20.475Z",
        "lkr": "2024-12-05T22:31:20.475Z",
        "ltc": "2024-12-05T16:26:24.361Z",
        "mmk": "2024-12-05T22:31:20.475Z",
        "mxn": "2026-02-10T01:52:35.741Z",
        "myr": "2026-02-27T16:47:36.546Z",
        "ngn": "2026-02-26T05:02:41.212Z",
        "nok": "2026-02-27T13:12:54.802Z",
        "nzd": "2024-12-05T22:31:20.475Z",
        "php": "2024-12-05T22:31:20.475Z",
        "pkr": "2024-12-05T22:31:20.475Z",
        "pln": "2026-01-30T12:18:28.920Z",
        "rub": "2025-07-10T21:17:21.944Z",
        "sar": "2024-12-05T22:31:20.475Z",
        "sek": "2026-01-30T12:08:15.170Z",
        "sgd": "2024-12-05T22:31:20.475Z",
        "sol": "2025-09-18T20:48:14.980Z",
        "thb": "2025-12-29T01:55:58.881Z",
        "try": "2024-12-05T22:31:20.475Z",
        "twd": "2025-06-27T03:12:25.227Z",
        "uah": "2024-12-05T22:31:20.475Z",
        "usd": "2024-12-05T22:31:20.475Z",
        "vef": "2024-12-05T22:31:20.475Z",
        "vnd": "2025-01-27T04:55:39.947Z",
        "xag": "2026-02-02T11:23:03.804Z",
        "xau": "2026-02-27T21:57:05.288Z",
        "xdr": "2025-09-17T23:33:22.311Z",
        "xlm": "2024-11-24T07:50:38.364Z",
        "xrp": "2025-07-18T03:42:37.030Z",
        "yfi": "2024-12-07T15:35:58.949Z",
        "zar": "2026-01-30T12:03:36.092Z",
        "bits": "2025-10-05T04:53:20.197Z",
        "link": "2024-12-16T10:36:06.657Z",
        "sats": "2025-10-05T04:53:20.197Z"
      },
      "market_cap": {
        "aed": 6918230514,
        "ars": 2631659095510,
        "aud": 2647264438,
        "bch": 4239459,
        "bdt": 229826106171,
        "bhd": 708524762,
        "bmd": 1883793196,
        "bnb": 3092006,
        "brl": 9663859098,
        "btc": 28664,
        "cad": 2571095144,
        "chf": 1449226595,
        "clp": 1645794764054,
        "cny": 12919430500,
        "czk": 38653929358,
        "dkk": 11913673313,
        "dot": 1194407139,
        "eos": 23973807121,
        "eth": 978144,
        "eur": 1594003638,
        "gbp": 1397162319,
        "gel": 5029727835,
        "hkd": 14737196745,
        "huf": 600512701674,
        "idr": 31652340994521,
        "ils": 5906614730,
        "inr": 171569291061,
        "jpy": 293956509348,
        "krw": 2712285444320,
        "kwd": 577457966,
        "lkr": 581610072715,
        "ltc": 35090681,
        "mmk": 3955777333329,
        "mxn": 32466798983,
        "myr": 7330404466,
        "ngn": 2556140582251,
        "nok": 17913366264,
        "nzd": 3141488886,
        "php": 108771161062,
        "pkr": 525662931233,
        "pln": 6732693838,
        "rub": 145208982917,
        "sar": 7060108399,
        "sek": 17012347978,
        "sgd": 2382244876,
        "sol": 23063918,
        "thb": 58242240202,
        "try": 82736197190,
        "twd": 59132268438,
        "uah": 81180564536,
        "usd": 1883793196,
        "vef": 188624213,
        "vnd": 49063393802826,
        "xag": 24521713,
        "xau": 356903,
        "xdr": 1300222321,
        "xlm": 12252559393,
        "xrp": 1407953908,
        "yfi": 725326,
        "zar": 30006037606,
        "bits": 28664259501,
        "link": 219727403,
        "sats": 2866425950071
      },
      "market_cap_rank": 42,
      "market_cap_rank_with_rehypothecated": 53,
      "fully_diluted_valuation": {
        "aed": 6918230514,
        "ars": 2631659095510,
        "aud": 2647264438,
        "bch": 4239459,
        "bdt": 229826106171,
        "bhd": 708524762,
        "bmd": 1883793196,
        "bnb": 3092006,
        "brl": 9663859098,
        "btc": 28664,
        "cad": 2571095144,
        "chf": 1449226595,
        "clp": 1645794764054,
        "cny": 12919430500,
        "czk": 38653929358,
        "dkk": 11913673313,
        "dot": 1194407139,
        "eos": 23973807121,
        "eth": 978144,
        "eur": 1594003638,
        "gbp": 1397162319,
        "gel": 5029727835,
        "hkd": 14737196745,
        "huf": 600512701674,
        "idr": 31652340994521,
        "ils": 5906614730,
        "inr": 171569291061,
        "jpy": 293956509348,
        "krw": 2712285444320,
        "kwd": 577457966,
        "lkr": 581610072715,
        "ltc": 35090681,
        "mmk": 3955777333329,
        "mxn": 32466798983,
        "myr": 7330404466,
        "ngn": 2556140582251,
        "nok": 17913366264,
        "nzd": 3141488886,
        "php": 108771161062,
        "pkr": 525662931233,
        "pln": 6732693838,
        "rub": 145208982917,
        "sar": 7060108399,
        "sek": 17012347978,
        "sgd": 2382244876,
        "sol": 23063918,
        "thb": 58242240202,
        "try": 82736197190,
        "twd": 59132268438,
        "uah": 81180564536,
        "usd": 1883793196,
        "vef": 188624213,
        "vnd": 49063393802826,
        "xag": 24521713,
        "xau": 356903,
        "xdr": 1300222321,
        "xlm": 12252559393,
        "xrp": 1407953908,
        "yfi": 725326,
        "zar": 30006037606,
        "bits": 28664259501,
        "link": 219727403,
        "sats": 2866425950071
      },
      "market_cap_fdv_ratio": null,
      "total_volume": {
        "aed": 410182,
        "ars": 156030959,
        "aud": 156956,
        "bch": 251.357,
        "bdt": 13626380,
        "bhd": 42008,
        "bmd": 111690,
        "bnb": 183.325,
        "brl": 572970,
        "btc": 1.699503,
        "cad": 152440,
        "chf": 85925,
        "clp": 97579103,
        "cny": 765992,
        "czk": 2291790,
        "dkk": 706361,
        "dot": 70816,
        "eos": 1421406,
        "eth": 57.994,
        "eur": 94508,
        "gbp": 82838,
        "gel": 298212,
        "hkd": 873768,
        "huf": 35604373,
        "idr": 1876665986,
        "ils": 350203,
        "inr": 10172336,
        "jpy": 17428669,
        "krw": 160811292,
        "kwd": 34237,
        "lkr": 34483637,
        "ltc": 2081,
        "mmk": 234537874,
        "mxn": 1924955,
        "myr": 434619,
        "ngn": 151553469,
        "nok": 1062083,
        "nzd": 186259,
        "php": 6449038,
        "pkr": 31166533,
        "pln": 399181,
        "rub": 8609435,
        "sar": 418594,
        "sek": 1008661,
        "sgd": 141243,
        "sol": 1367,
        "thb": 3453180,
        "try": 4905426,
        "twd": 3505950,
        "uah": 4813192,
        "usd": 111690,
        "vef": 11183.52,
        "vnd": 2908966585,
        "xag": 1453.89,
        "xau": 21.16,
        "xdr": 77090,
        "xlm": 726454,
        "xrp": 83478,
        "yfi": 43.004533,
        "zar": 1779057,
        "bits": 1699503,
        "link": 13028,
        "sats": 169950276
      },
      "high_24h": {
        "aed": 4.1,
        "ars": 1560.33,
        "aud": 1.57,
        "bch": 0.00252441,
        "bdt": 136.27,
        "bhd": 0.420091,
        "bmd": 1.12,
        "bnb": 0.00189326,
        "brl": 5.73,
        "btc": 0.00001762,
        "cad": 1.52,
        "chf": 0.859371,
        "clp": 975.81,
        "cny": 7.66,
        "czk": 22.92,
        "dkk": 7.06,
        "dot": 0.76392118,
        "eos": 15.048786,
        "eth": 0.00060463,
        "eur": 0.945178,
        "gbp": 0.828933,
        "gel": 2.98,
        "hkd": 8.74,
        "huf": 356.05,
        "idr": 18766.95,
        "ils": 3.5,
        "inr": 101.73,
        "jpy": 174.31,
        "krw": 1608.35,
        "kwd": 0.34238,
        "lkr": 344.84,
        "ltc": 0.02164989,
        "mmk": 2345.41,
        "mxn": 19.25,
        "myr": 4.35,
        "ngn": 1515.56,
        "nok": 10.62,
        "nzd": 1.86,
        "php": 64.49,
        "pkr": 311.67,
        "pln": 3.99,
        "rub": 86.1,
        "sar": 4.19,
        "sek": 10.09,
        "sgd": 1.41,
        "sol": 0.01433221,
        "thb": 34.62,
        "try": 49.06,
        "twd": 35.06,
        "uah": 48.13,
        "usd": 1.12,
        "vef": 0.111837,
        "vnd": 29090,
        "xag": 0.01453914,
        "xau": 0.00021161,
        "xdr": 0.770913,
        "xlm": 7.530738,
        "xrp": 0.87700509,
        "yfi": 0.00044287,
        "zar": 17.79,
        "bits": 17.62,
        "link": 0.13571169,
        "sats": 1761.57
      },
      "low_24h": {
        "aed": 4.1,
        "ars": 1560.03,
        "aud": 1.57,
        "bch": 0.00248233,
        "bdt": 136.24,
        "bhd": 0.420009,
        "bmd": 1.12,
        "bnb": 0.00182182,
        "brl": 5.73,
        "btc": 0.00001691,
        "cad": 1.52,
        "chf": 0.859204,
        "clp": 975.62,
        "cny": 7.66,
        "czk": 22.91,
        "dkk": 7.06,
        "dot": 0.69929828,
        "eos": 14.096382,
        "eth": 0.00057504,
        "eur": 0.944917,
        "gbp": 0.828147,
        "gel": 2.98,
        "hkd": 8.74,
        "huf": 355.98,
        "idr": 18763.3,
        "ils": 3.5,
        "inr": 101.71,
        "jpy": 174.27,
        "krw": 1607.96,
        "kwd": 0.342313,
        "lkr": 344.77,
        "ltc": 0.02073603,
        "mmk": 2344.96,
        "mxn": 19.25,
        "myr": 4.35,
        "ngn": 1515.26,
        "nok": 10.62,
        "nzd": 1.86,
        "php": 64.48,
        "pkr": 311.61,
        "pln": 3.99,
        "rub": 86.08,
        "sar": 4.19,
        "sek": 10.08,
        "sgd": 1.41,
        "sol": 0.01354415,
        "thb": 34.53,
        "try": 49.05,
        "twd": 35.05,
        "uah": 48.12,
        "usd": 1.12,
        "vef": 0.111815,
        "vnd": 29084,
        "xag": 0.01453631,
        "xau": 0.00021157,
        "xdr": 0.770763,
        "xlm": 7.217975,
        "xrp": 0.83093027,
        "yfi": 0.00042698,
        "zar": 17.79,
        "bits": 16.91,
        "link": 0.1294433,
        "sats": 1691.44
      },
      "price_change_24h": 0.00008896,
      "price_change_percentage_24h": 0.00797,
      "price_change_percentage_7d": 0.16974,
      "price_change_percentage_14d": 0.16974,
      "price_change_percentage_30d": 0.40699,
      "price_change_percentage_60d": 0.55221,
      "price_change_percentage_200d": 1.91719,
      "price_change_percentage_1y": 4.37093,
      "market_cap_change_24h": 150034,
      "market_cap_change_percentage_24h": 0.00797,
      "price_change_24h_in_currency": {
        "aed": 0.00032669,
        "ars": 0.12427,
        "aud": 0.00012501,
        "bch": 0.00000168,
        "bdt": 0.01085269,
        "bhd": 0.00003346,
        "bmd": 0.00008896,
        "bnb": -0.000054456455096747,
        "brl": 0.00045634,
        "btc": -5.7156716109e-7,
        "cad": 0.00012141,
        "chf": -0.000043246724281465,
        "clp": 0.077717,
        "cny": 0.00061007,
        "czk": 0.00182529,
        "dkk": 0.00056258,
        "dot": -0.04502838432582623,
        "eos": -0.5049275811602207,
        "eth": -0.00002232034507071,
        "eur": -0.00000402263418775,
        "gbp": 0.00006598,
        "gel": 0.00023751,
        "hkd": 0.00069591,
        "huf": 0.02835701,
        "idr": 1.49,
        "ils": 0.00027892,
        "inr": 0.00436041,
        "jpy": -0.008455209002391939,
        "krw": -0.09528453630991862,
        "kwd": 0.00002727,
        "lkr": 0.0274644,
        "ltc": -0.000717237296048494,
        "mmk": 0.186797,
        "mxn": 0.0010864,
        "myr": 0.00034615,
        "ngn": 0.120704,
        "nok": 0.00084589,
        "nzd": 0.00014835,
        "php": 0.00513632,
        "pkr": 0.0248225,
        "pln": 0.00031793,
        "rub": 0.00685696,
        "sar": -0.001677989385137302,
        "sek": 0.00080335,
        "sgd": 0.00011249,
        "sol": -0.000629122561792386,
        "thb": 0.00275139,
        "try": 0.00390691,
        "twd": 0.0027923,
        "uah": 0.00383345,
        "usd": 0.00008896,
        "vef": 0.00000891,
        "vnd": 2.32,
        "xag": 0.00000116,
        "xau": 1.6853e-8,
        "xdr": 0.0000614,
        "xlm": -0.24480955318759268,
        "xrp": -0.032287194306030664,
        "yfi": -0.000011183899619161,
        "zar": 0.00141692,
        "bits": -0.5715671610899271,
        "link": -0.004669493486853693,
        "sats": -57.15671610899244
      },
      "price_change_percentage_1h_in_currency": {},
      "price_change_percentage_24h_in_currency": {
        "aed": 0.00797,
        "ars": 0.00797,
        "aud": 0.00797,
        "bch": 0.06686,
        "bdt": 0.00797,
        "bhd": 0.00797,
        "bmd": 0.00797,
        "bnb": -2.8848,
        "brl": 0.00797,
        "btc": -3.25372,
        "cad": 0.00797,
        "chf": -0.00503,
        "clp": 0.00797,
        "cny": 0.00797,
        "czk": 0.00797,
        "dkk": 0.00797,
        "dot": -5.97834,
        "eos": -3.43045,
        "eth": -3.70609,
        "eur": -0.00043,
        "gbp": 0.00797,
        "gel": 0.00797,
        "hkd": 0.00797,
        "huf": 0.00797,
        "idr": 0.00797,
        "ils": 0.00797,
        "inr": 0.00429,
        "jpy": -0.00485,
        "krw": -0.00592,
        "kwd": 0.00797,
        "lkr": 0.00797,
        "ltc": -3.3325,
        "mmk": 0.00797,
        "mxn": 0.00564,
        "myr": 0.00797,
        "ngn": 0.00797,
        "nok": 0.00797,
        "nzd": 0.00797,
        "php": 0.00797,
        "pkr": 0.00797,
        "pln": 0.00797,
        "rub": 0.00797,
        "sar": -0.04007,
        "sek": 0.00797,
        "sgd": 0.00797,
        "sol": -4.39832,
        "thb": 0.00797,
        "try": 0.00797,
        "twd": 0.00797,
        "uah": 0.00797,
        "usd": 0.00797,
        "vef": 0.00797,
        "vnd": 0.00797,
        "xag": 0.00797,
        "xau": 0.00797,
        "xdr": 0.00797,
        "xlm": -3.26006,
        "xrp": -3.72374,
        "yfi": -2.53471,
        "zar": 0.00797,
        "bits": -3.25372,
        "link": -3.46027,
        "sats": -3.25372
      },
      "price_change_percentage_7d_in_currency": {
        "aed": 0.15883,
        "ars": -1.20965,
        "aud": -0.40179,
        "bch": 18.11559,
        "bdt": 0.30459,
        "bhd": -0.07415,
        "bmd": 0.16974,
        "bnb": 4.9071,
        "brl": -1.11024,
        "btc": 5.99011,
        "cad": 0.85935,
        "chf": 0.4256,
        "clp": 2.5983,
        "cny": -0.60131,
        "czk": 1.00186,
        "dkk": 0.95443,
        "dot": -17.34211,
        "eos": 4.55991,
        "eth": 7.26804,
        "eur": 0.91608,
        "gbp": 1.6363,
        "gel": -0.57502,
        "hkd": 0.25926,
        "huf": 0.87735,
        "idr": 0.22843,
        "ils": 1.89502,
        "inr": 0.60864,
        "jpy": 0.69061,
        "krw": -0.93383,
        "kwd": -0.00901,
        "lkr": 0.23271,
        "ltc": 0.41893,
        "mmk": 0.16974,
        "mxn": 0.41155,
        "myr": -0.69032,
        "ngn": 0.25703,
        "nok": -0.74789,
        "nzd": 0.90393,
        "php": -1.03349,
        "pkr": 0.27145,
        "pln": 1.29761,
        "rub": 0.27939,
        "sar": 0.09803,
        "sek": 1.26828,
        "sgd": 0.13965,
        "sol": 5.66677,
        "thb": -0.56079,
        "try": 0.90076,
        "twd": -0.29369,
        "uah": 0.45001,
        "usd": 0.16974,
        "vef": 0.16974,
        "vnd": 0.82174,
        "xag": 6.24193,
        "xau": -4.55563,
        "xdr": 0.22187,
        "xlm": 3.48761,
        "xrp": 8.08534,
        "yfi": 18.29705,
        "zar": 0.38584,
        "bits": 5.99011,
        "link": 1.44182,
        "sats": 5.99011
      },
      "price_change_percentage_14d_in_currency": {
        "aed": 0.15883,
        "ars": -1.20965,
        "aud": -0.40179,
        "bch": 18.11559,
        "bdt": 0.30459,
        "bhd": -0.07415,
        "bmd": 0.16974,
        "bnb": 4.9071,
        "brl": -1.11024,
        "btc": 5.99011,
        "cad": 0.85935,
        "chf": 0.4256,
        "clp": 2.5983,
        "cny": -0.60131,
        "czk": 1.00186,
        "dkk": 0.95443,
        "dot": -17.34211,
        "eos": 4.55991,
        "eth": 7.26804,
        "eur": 0.91608,
        "gbp": 1.6363,
        "gel": -0.57502,
        "hkd": 0.25926,
        "huf": 0.87735,
        "idr": 0.22843,
        "ils": 1.89502,
        "inr": 0.60864,
        "jpy": 0.69061,
        "krw": -0.93383,
        "kwd": -0.00901,
        "lkr": 0.23271,
        "ltc": 0.41893,
        "mmk": 0.16974,
        "mxn": 0.41155,
        "myr": -0.69032,
        "ngn": 0.25703,
        "nok": -0.74789,
        "nzd": 0.90393,
        "php": -1.03349,
        "pkr": 0.27145,
        "pln": 1.29761,
        "rub": 0.27939,
        "sar": 0.09803,
        "sek": 1.26828,
        "sgd": 0.13965,
        "sol": 5.66677,
        "thb": -0.56079,
        "try": 0.90076,
        "twd": -0.29369,
        "uah": 0.45001,
        "usd": 0.16974,
        "vef": 0.16974,
        "vnd": 0.82174,
        "xag": 6.24193,
        "xau": -4.55563,
        "xdr": 0.22187,
        "xlm": 3.48761,
        "xrp": 8.08534,
        "yfi": 18.29705,
        "zar": 0.38584,
        "bits": 5.99011,
        "link": 1.44182,
        "sats": 5.99011
      },
      "price_change_percentage_30d_in_currency": {
        "aed": 0.40699,
        "ars": -2.7247,
        "aud": -5.44939,
        "bch": 35.47308,
        "bdt": 0.18082,
        "bhd": 0.17474,
        "bmd": 0.40699,
        "bnb": 54.14018,
        "brl": -4.05724,
        "btc": 46.13802,
        "cad": -1.35771,
        "chf": -3.75309,
        "clp": -0.87462,
        "cny": -1.17803,
        "czk": -1.48136,
        "dkk": -1.31803,
        "dot": 36.70393,
        "eos": 104.53627,
        "eth": 72.67498,
        "eur": -1.34467,
        "gbp": -0.33464,
        "gel": -0.52443,
        "hkd": 0.71184,
        "huf": -3.54882,
        "idr": -0.11618,
        "ils": 0.31741,
        "inr": 0.79866,
        "jpy": -1.02487,
        "krw": -1.80523,
        "kwd": -0.10431,
        "lkr": 0.20179,
        "ltc": 34.98017,
        "mmk": 0.40699,
        "mxn": -1.95799,
        "myr": -3.71766,
        "ngn": -4.36174,
        "nok": -5.56949,
        "nzd": -3.63087,
        "php": -2.34636,
        "pkr": -0.08548,
        "pln": -1.14021,
        "rub": -1.09091,
        "sar": 0.34662,
        "sek": -1.73195,
        "sgd": -1.40186,
        "sol": 75.9643,
        "thb": -1.05858,
        "try": 1.89387,
        "twd": -0.0494,
        "uah": -0.49439,
        "usd": 0.40699,
        "vef": 0.40699,
        "vnd": -0.46624,
        "xag": 18.7505,
        "xau": -12.31974,
        "xdr": -1.13412,
        "xlm": 48.83469,
        "xrp": 55.68022,
        "yfi": 32.2648,
        "zar": -2.14294,
        "bits": 46.13802,
        "link": 61.57084,
        "sats": 46.13802
      },
      "price_change_percentage_60d_in_currency": {
        "aed": 0.55221,
        "ars": -3.2142,
        "aud": -5.36242,
        "bch": 34.46458,
        "bdt": 0.27348,
        "bhd": 0.31803,
        "bmd": 0.55221,
        "bnb": 41.85853,
        "brl": -5.83211,
        "btc": 35.0457,
        "cad": 0.21702,
        "chf": -2.30099,
        "clp": -2.48823,
        "cny": -1.434,
        "czk": -0.03508,
        "dkk": 0.02132,
        "dot": 15.04405,
        "eos": 107.8374,
        "eth": 54.68461,
        "eur": -0.04809,
        "gbp": 0.42547,
        "gel": -0.38055,
        "hkd": 1.09327,
        "huf": -2.43016,
        "idr": 1.0112,
        "ils": -0.76486,
        "inr": 2.01569,
        "jpy": 0.34547,
        "krw": 0.52007,
        "kwd": 0.17314,
        "lkr": 0.12271,
        "ltc": 46.90459,
        "mmk": 0.56179,
        "mxn": -3.69081,
        "myr": -3.38795,
        "ngn": -6.3822,
        "nok": -4.88532,
        "nzd": -2.88589,
        "php": -1.40716,
        "pkr": 0.16404,
        "pln": -0.04645,
        "rub": -2.49699,
        "sar": 0.50434,
        "sek": -1.26505,
        "sgd": -0.982,
        "sol": 53.51697,
        "thb": -1.15019,
        "try": 2.78603,
        "twd": 0.91614,
        "uah": 2.13325,
        "usd": 0.55221,
        "vef": 0.55221,
        "vnd": -0.29932,
        "xag": -1.58585,
        "xau": -17.29347,
        "xdr": 0.163,
        "xlm": 37.30597,
        "xrp": 40.77157,
        "yfi": 27.13207,
        "zar": -3.55292,
        "bits": 35.0457,
        "link": 45.17949,
        "sats": 35.0457
      },
      "price_change_percentage_200d_in_currency": {
        "aed": 1.90331,
        "ars": 8.12432,
        "aud": -6.49772,
        "bch": 41.41573,
        "bdt": 2.21725,
        "bhd": 1.66526,
        "bmd": 1.91719,
        "bnb": 39.8262,
        "brl": -3.21988,
        "btc": 85.17844,
        "cad": 0.97135,
        "chf": -2.79647,
        "clp": -6.94365,
        "cny": -2.68723,
        "czk": -0.17332,
        "dkk": 0.89964,
        "dot": 169.2057,
        "eos": 612.01658,
        "eth": 144.53847,
        "eur": 0.74562,
        "gbp": 2.06457,
        "gel": 0.97176,
        "hkd": 1.5693,
        "huf": -4.04774,
        "idr": 5.51297,
        "ils": -6.53753,
        "inr": 5.99843,
        "jpy": 7.40242,
        "krw": 6.08748,
        "kwd": 2.27452,
        "lkr": 4.49019,
        "ltc": 148.78551,
        "mmk": 1.96089,
        "mxn": -5.48316,
        "myr": -6.05464,
        "ngn": -9.87775,
        "nok": -5.11392,
        "nzd": 1.25645,
        "php": 3.3736,
        "pkr": 0.16912,
        "pln": -0.00441,
        "rub": -1.11881,
        "sar": 1.77345,
        "sek": -3.56314,
        "sgd": 0.46847,
        "sol": 147.37389,
        "thb": -2.6283,
        "try": 9.82525,
        "twd": 6.8074,
        "uah": 5.83794,
        "usd": 1.91719,
        "vef": 1.91719,
        "vnd": 1.04428,
        "xag": -49.41429,
        "xau": -35.3168,
        "xdr": 0.15814,
        "xlm": 195.23167,
        "xrp": 146.36317,
        "yfi": 131.43813,
        "zar": -7.67845,
        "bits": 85.17844,
        "link": 186.30169,
        "sats": 85.17844
      },
      "price_change_percentage_1y_in_currency": {
        "aed": 4.36737,
        "ars": 37.12141,
        "aud": -8.97645,
        "bch": -24.27884,
        "bdt": 4.86438,
        "bhd": 4.16128,
        "bmd": 4.37093,
        "bnb": 1.70301,
        "brl": -9.03451,
        "btc": 35.34253,
        "cad": -1.53067,
        "chf": -11.11677,
        "clp": -5.15425,
        "cny": -1.72758,
        "czk": -11.40019,
        "dkk": -8.15864,
        "dot": 216.20141,
        "eos": 646.35031,
        "eth": 22.2653,
        "eur": -8.3439,
        "gbp": -2.67326,
        "gel": -0.02857,
        "hkd": 4.96666,
        "huf": -14.43692,
        "idr": 6.08188,
        "ils": -9.07338,
        "inr": 8.67241,
        "jpy": 8.13373,
        "krw": 2.8005,
        "kwd": 3.66078,
        "lkr": 9.2015,
        "ltc": 149.81134,
        "mmk": 4.46545,
        "mxn": -12.44825,
        "myr": -8.98855,
        "ngn": -5.74236,
        "nok": -11.84267,
        "nzd": -2.6347,
        "php": 4.01155,
        "pkr": 4.10787,
        "pln": -7.73072,
        "rub": -9.94814,
        "sar": 4.29393,
        "sek": -12.36696,
        "sgd": -2.32556,
        "sol": 90.93832,
        "thb": -5.75028,
        "try": 25.91944,
        "twd": -0.47985,
        "uah": 8.5577,
        "usd": 4.37093,
        "vef": 4.37093,
        "vnd": 6.37217,
        "xag": -57.67636,
        "xau": -43.48638,
        "xdr": -5.37613,
        "xlm": 97.47893,
        "xrp": 70.69951,
        "yfi": 125.23272,
        "zar": -11.10262,
        "bits": 35.34253,
        "link": 80.57595,
        "sats": 35.34253
      },
      "market_cap_change_24h_in_currency": {
        "aed": 551001,
        "ars": 209597770,
        "aud": 210841,
        "bch": 3352,
        "bdt": 18304437,
        "bhd": 56430,
        "bmd": 150034,
        "bnb": -92250.19648461277,
        "brl": 769675,
        "btc": -963.0283735813537,
        "cad": 204774,
        "chf": -72941.06006383896,
        "clp": 131078874,
        "cny": 1028965,
        "czk": 3078582,
        "dkk": 948861,
        "dot": -76705863.96423364,
        "eos": -850793083.4932632,
        "eth": -37557.34935572953,
        "eur": -6784.680383682251,
        "gbp": 111277,
        "gel": 400591,
        "hkd": 1173740,
        "huf": 47827670,
        "idr": 2520942049,
        "ils": 470431,
        "inr": 7354385,
        "jpy": -14260777.387084961,
        "krw": -160709399.42041016,
        "kwd": 45991,
        "lkr": 46322175,
        "ltc": -1205864.8306584135,
        "mmk": 315056805,
        "mxn": 1832352,
        "myr": 583828,
        "ngn": 203583118,
        "nok": 1426705,
        "nzd": 250203,
        "php": 8663049,
        "pkr": 41866281,
        "pln": 536224,
        "rub": 11565130,
        "sar": -2830140.9311714172,
        "sek": 1354944,
        "sgd": 189733,
        "sol": -1059389.5798963867,
        "thb": 4640571,
        "try": 6589502,
        "twd": 4709573,
        "uah": 6465604,
        "usd": 150034,
        "vef": 15022.92,
        "vnd": 3907640592,
        "xag": 1953.03,
        "xau": 28.43,
        "xdr": 103556,
        "xlm": -409403114.6238289,
        "xrp": -53992988.79163504,
        "yfi": -18792.19543645368,
        "zar": 2389823,
        "bits": -963028373.5813713,
        "link": -7845570.208159357,
        "sats": -96302837358.13525
      },
      "market_cap_change_percentage_24h_in_currency": {
        "aed": 0.00797,
        "ars": 0.00797,
        "aud": 0.00797,
        "bch": 0.07914,
        "bdt": 0.00797,
        "bhd": 0.00797,
        "bmd": 0.00797,
        "bnb": -2.89707,
        "brl": 0.00797,
        "btc": -3.25048,
        "cad": 0.00797,
        "chf": -0.00503,
        "clp": 0.00797,
        "cny": 0.00797,
        "czk": 0.00797,
        "dkk": 0.00797,
        "dot": -6.03454,
        "eos": -3.42722,
        "eth": -3.69768,
        "eur": -0.00043,
        "gbp": 0.00797,
        "gel": 0.00797,
        "hkd": 0.00797,
        "huf": 0.00797,
        "idr": 0.00797,
        "ils": 0.00797,
        "inr": 0.00429,
        "jpy": -0.00485,
        "krw": -0.00592,
        "kwd": 0.00797,
        "lkr": 0.00797,
        "ltc": -3.32226,
        "mmk": 0.00797,
        "mxn": 0.00564,
        "myr": 0.00797,
        "ngn": 0.00797,
        "nok": 0.00797,
        "nzd": 0.00797,
        "php": 0.00797,
        "pkr": 0.00797,
        "pln": 0.00797,
        "rub": 0.00797,
        "sar": -0.04007,
        "sek": 0.00797,
        "sgd": 0.00797,
        "sol": -4.39156,
        "thb": 0.00797,
        "try": 0.00797,
        "twd": 0.00797,
        "uah": 0.00797,
        "usd": 0.00797,
        "vef": 0.00797,
        "vnd": 0.00797,
        "xag": 0.00797,
        "xau": 0.00797,
        "xdr": 0.00797,
        "xlm": -3.23333,
        "xrp": -3.69323,
        "yfi": -2.52543,
        "zar": 0.00797,
        "bits": -3.25048,
        "link": -3.4475,
        "sats": -3.25048
      },
      "total_supply": 1686626242.240764,
      "max_supply": null,
      "max_supply_infinite": true,
      "circulating_supply": 1686626242.240764,
      "last_updated": "2026-02-28T19:21:48.538Z"
    },
    "community_data": {
      "facebook_likes": null,
      "reddit_average_posts_48h": 0,
      "reddit_average_comments_48h": 0,
      "reddit_subscribers": 0,
      "reddit_accounts_active_48h": 0,
      "telegram_channel_user_count": null
    },
    "developer_data": {
      "forks": 0,
      "stars": 0,
      "subscribers": 0,
      "total_issues": 0,
      "closed_issues": 0,
      "pull_requests_merged": 0,
      "pull_request_contributors": 0,
      "code_additions_deletions_4_weeks": {
        "additions": null,
        "deletions": null
      },
      "commit_count_4_weeks": 0,
      "last_4_weeks_commit_activity_series": []
    },
    "status_updates": [],
    "last_updated": "2026-02-28T19:21:48.538Z",
    "tickers": [
      {
        "base": "USYC",
        "target": "USDC",
        "market": {
          "name": "Deribit Spot",
          "identifier": "deribit_spot",
          "has_trading_incentive": false
        },
        "last": 1.1169,
        "volume": 100000,
        "converted_last": {
          "btc": 0.00001723,
          "eth": 0.00058899,
          "usd": 1.12
        },
        "converted_volume": {
          "btc": 1.722755,
          "eth": 58.899,
          "usd": 111690
        },
        "trust_score": "red",
        "bid_ask_spread_percentage": 0.143074,
        "timestamp": "2026-02-28T11:21:51+00:00",
        "last_traded_at": "2026-02-28T11:21:51+00:00",
        "last_fetch_at": "2026-02-28T15:49:20+00:00",
        "is_anomaly": false,
        "is_stale": true,
        "trade_url": "https://www.deribit.com/spot/USYC_USDC",
        "token_info_url": null,
        "coin_id": "hashnote-usyc",
        "target_coin_id": "usd-coin",
        "coin_mcap_usd": 1883793196.499353
      }
    ]
  },
  "chart": {
    "prices": [
      [
        1769774603404,
        1.11345444
      ],
      [
        1769778286275,
        1.1135638420443519
      ],
      [
        1769781873914,
        1.1134530829038896
      ],
      [
        1769785497350,
        1.1134991453953844
      ],
      [
        1769789046967,
        1.1134837518166922
      ],
      [
        1769792638874,
        1.1134634113278887
      ],
      [
        1769796284193,
        1.113472068885723
      ],
      [
        1769799861666,
        1.1136011615436339
      ],
      [
        1769803453148,
        1.1135671025043865
      ],
      [
        1769807052792,
        1.1135758592467218
      ],
      [
        1769810645281,
        1.1135808868514003
      ],
      [
        1769814262364,
        1.11356583
      ],
      [
        1769817890273,
        1.113469514555787
      ],
      [
        1769857469320,
        1.1135698590054597
      ],
      [
        1769861099837,
        1.113468321402659
      ],
      [
        1769864667477,
        1.1135756936101142
      ],
      [
        1769868255014,
        1.1135700938285702
      ],
      [
        1769871974092,
        1.1135771728164403
      ],
      [
        1769875463649,
        1.1135782214130188
      ],
      [
        1769879054592,
        1.1135782214130188
      ],
      [
        1769882746846,
        1.1135782214130188
      ],
      [
        1769886276880,
        1.1135782214130188
      ],
      [
        1770015894890,
        1.1138689156100647
      ],
      [
        1770019687034,
        1.1137622278721646
      ],
      [
        1770023081647,
        1.113765640505923
      ],
      [
        1770026676332,
        1.1138633284021748
      ],
      [
        1770030269152,
        1.113864560069457
      ],
      [
        1770033885850,
        1.1137733347819267
      ],
      [
        1770037490351,
        1.1138737522022764
      ],
      [
        1770041142246,
        1.1138682747733397
      ],
      [
        1770044668788,
        1.1137723173065612
      ],
      [
        1770131039068,
        1.1141755019401505
      ],
      [
        1770134678413,
        1.1141682368217127
      ],
      [
        1770138380251,
        1.1140615189884702
      ],
      [
        1770141890524,
        1.1140615189884702
      ],
      [
        1770145463602,
        1.1140615189884702
      ],
      [
        1770149061629,
        1.114162868462461
      ],
      [
        1770152753965,
        1.1140585675075871
      ],
      [
        1770156263716,
        1.1139569289759783
      ],
      [
        1770159995754,
        1.1141698148712649
      ],
      [
        1770163492954,
        1.114164184615285
      ],
      [
        1770167073296,
        1.1141677146286362
      ],
      [
        1770170669741,
        1.1141006321434241
      ],
      [
        1770174341598,
        1.1139813665847835
      ],
      [
        1770177857465,
        1.1140694864458414
      ],
      [
        1770213880162,
        1.1141574603187192
      ],
      [
        1770217442090,
        1.1143681821823144
      ],
      [
        1770221048894,
        1.1141736929434807
      ],
      [
        1770224798844,
        1.1141589302842605
      ],
      [
        1770228148558,
        1.1141632415351446
      ],
      [
        1770231747941,
        1.1140560959081425
      ],
      [
        1770235479811,
        1.114154480437968
      ],
      [
        1770239087410,
        1.1140593368905016
      ],
      [
        1770242669050,
        1.114161480557615
      ],
      [
        1770246267978,
        1.1142591398914765
      ],
      [
        1770249873350,
        1.1142783612683558
      ],
      [
        1770253461880,
        1.1142009465447091
      ],
      [
        1770257050719,
        1.1140700956757454
      ],
      [
        1770260645429,
        1.1142193892517482
      ],
      [
        1770307428609,
        1.114497512745382
      ],
      [
        1770311067423,
        1.1144496623583364
      ],
      [
        1770314693685,
        1.1143786422191022
      ],
      [
        1770318235558,
        1.1144549293831798
      ],
      [
        1770321835648,
        1.1143677371111658
      ],
      [
        1770325479985,
        1.1143711115348547
      ],
      [
        1770329055515,
        1.1143456937845244
      ],
      [
        1770332684285,
        1.1143456937845244
      ],
      [
        1770336261842,
        1.1143456937845244
      ],
      [
        1770339834994,
        1.114465985470389
      ],
      [
        1770343405097,
        1.1145782433980183
      ],
      [
        1770347049228,
        1.11448543745295
      ],
      [
        1770350692646,
        1.1143607350317724
      ],
      [
        1770354244803,
        1.114369676393759
      ],
      [
        1770357868569,
        1.1144110694735676
      ],
      [
        1770361598826,
        1.114493962815157
      ],
      [
        1770365060818,
        1.11439676170504
      ],
      [
        1770368627575,
        1.11439676170504
      ],
      [
        1770415564999,
        1.1143815641680828
      ],
      [
        1770419035164,
        1.1143815641680828
      ],
      [
        1770422693822,
        1.1143794422487925
      ],
      [
        1770426270453,
        1.1144852385640494
      ],
      [
        1770429861511,
        1.1144873361543535
      ],
      [
        1770433615705,
        1.1143757685173863
      ],
      [
        1770437036736,
        1.114483568870886
      ],
      [
        1770440805143,
        1.1144804486066362
      ],
      [
        1770444441486,
        1.1144833579714757
      ],
      [
        1770447886454,
        1.1144865409223408
      ],
      [
        1770451494741,
        1.11437708
      ],
      [
        1770455096175,
        1.11437708
      ],
      [
        1770674904995,
        1.1149863803754492
      ],
      [
        1770678498005,
        1.1149863803754492
      ],
      [
        1770682109007,
        1.1149839716371481
      ],
      [
        1770685713364,
        1.114995586969414
      ],
      [
        1770689295853,
        1.115005924904621
      ],
      [
        1770692878161,
        1.1150667846288806
      ],
      [
        1770696495942,
        1.1150122225181052
      ],
      [
        1770700127935,
        1.1150112407719428
      ],
      [
        1770703678014,
        1.1150076044054593
      ],
      [
        1772060633596,
        1.1179916528975806
      ],
      [
        1772064341444,
        1.117991941927776
      ],
      [
        1772067836744,
        1.1181015238070395
      ],
      [
        1772071471654,
        1.1179926050367506
      ],
      [
        1772075035913,
        1.1178837265911166
      ],
      [
        1772078619946,
        1.1180964523440966
      ],
      [
        1772082265210,
        1.1178763799999998
      ],
      [
        1772085811884,
        1.1181
      ],
      [
        1772089469287,
        1.11798819
      ],
      [
        1772107478098,
        1.117986087957007
      ],
      [
        1772111050173,
        1.1178918365443795
      ],
      [
        1772114728053,
        1.1179896466037471
      ],
      [
        1772118242891,
        1.118074760119419
      ],
      [
        1772121838872,
        1.1180958435367827
      ],
      [
        1772125551137,
        1.1180958435367827
      ],
      [
        1772129062202,
        1.1180958435367827
      ],
      [
        1772132643980,
        1.1180958435367827
      ],
      [
        1772190262384,
        1.1181885260905522
      ],
      [
        1772193801836,
        1.1166982579567568
      ],
      [
        1772197455847,
        1.1167065280061585
      ],
      [
        1772201069388,
        1.1167049415700245
      ],
      [
        1772204773055,
        1.1167907647113264
      ],
      [
        1772208246400,
        1.1168964267284642
      ],
      [
        1772211993288,
        1.1168934288126293
      ],
      [
        1772215446979,
        1.1168176738774753
      ],
      [
        1772219146262,
        1.1168085388025586
      ],
      [
        1772222642877,
        1.1168809701113784
      ],
      [
        1772226303588,
        1.1167934553815233
      ],
      [
        1772229851179,
        1.116898900914697
      ],
      [
        1772233427500,
        1.116898900914697
      ],
      [
        1772237075012,
        1.116898900914697
      ],
      [
        1772269492758,
        1.1168112502521501
      ],
      [
        1772273024465,
        1.1167938118476473
      ],
      [
        1772276668930,
        1.1167149391773905
      ],
      [
        1772280257923,
        1.116802468185626
      ],
      [
        1772283826103,
        1.1168086427302506
      ],
      [
        1772287471078,
        1.1167814784193781
      ],
      [
        1772291037882,
        1.1167981468071357
      ],
      [
        1772294622193,
        1.1169002054638049
      ],
      [
        1772298204221,
        1.1169002054638049
      ],
      [
        1772301873903,
        1.1169002054638049
      ],
      [
        1772305416770,
        1.1169002054638049
      ],
      [
        1772306508000,
        1.1169002054638049
      ],
      [
        1772309048901,
        1.1169002054638049
      ]
    ],
    "market_caps": [
      [
        1769774603404,
        1698117266.9922326
      ],
      [
        1769778286275,
        1698284114.8612452
      ],
      [
        1769781873914,
        1698115197.2997007
      ],
      [
        1769785497350,
        1649608978.8227596
      ],
      [
        1769789046967,
        1649417925.7899044
      ],
      [
        1769792638874,
        1649556040.085595
      ],
      [
        1769796284193,
        1649560216.6037977
      ],
      [
        1769799861666,
        1649760112.08122
      ],
      [
        1769803453148,
        1649709654.8382268
      ],
      [
        1769807052792,
        1649722627.6373894
      ],
      [
        1769810645281,
        1649730075.853093
      ],
      [
        1769814262364,
        1649707769.6686966
      ],
      [
        1769817890273,
        1649565081.7984543
      ],
      [
        1769857469320,
        1649713738.4955325
      ],
      [
        1769861099837,
        1649563314.184962
      ],
      [
        1769864667477,
        1649722382.252707
      ],
      [
        1769868255014,
        1649714086.3775349
      ],
      [
        1769871974092,
        1649724573.6437352
      ],
      [
        1769875463649,
        1649726127.101892
      ],
      [
        1769879054592,
        1649726127.101892
      ],
      [
        1769882746846,
        1649726127.101892
      ],
      [
        1769886276880,
        1649726127.101892
      ],
      [
        1770015894890,
        1650156780.1109416
      ],
      [
        1770019687034,
        1649998726.0602512
      ],
      [
        1770023081647,
        1650003781.7545583
      ],
      [
        1770026676332,
        1650148502.8631864
      ],
      [
        1770030269152,
        1650150327.5340154
      ],
      [
        1770033885850,
        1650016677.569833
      ],
      [
        1770037490351,
        1650163945.348538
      ],
      [
        1770041142246,
        1650025637.1536
      ],
      [
        1770044668788,
        1650013673.1948237
      ],
      [
        1770131039068,
        1668631773.63522
      ],
      [
        1770134678413,
        1668620893.1164474
      ],
      [
        1770138380251,
        1668461068.4146378
      ],
      [
        1770141890524,
        1668461068.4146378
      ],
      [
        1770145463602,
        1668461068.4146378
      ],
      [
        1770149061629,
        1668612853.2566562
      ],
      [
        1770152753965,
        1668456648.164173
      ],
      [
        1770156263716,
        1668304430.418429
      ],
      [
        1770159995754,
        1668612122.9174302
      ],
      [
        1770163492954,
        1668614824.3773792
      ],
      [
        1770167073296,
        1668620111.0601583
      ],
      [
        1770170669741,
        1668519645.7689323
      ],
      [
        1770174341598,
        1668341029.1144626
      ],
      [
        1770177857465,
        1668473000.7830136
      ],
      [
        1770213880162,
        1668604753.8140922
      ],
      [
        1770217442090,
        1663252900.6965334
      ],
      [
        1770221048894,
        1662962615.3170538
      ],
      [
        1770224798844,
        1662952933.6848168
      ],
      [
        1770228148558,
        1662947016.042497
      ],
      [
        1770231747941,
        1662787095.5801601
      ],
      [
        1770235479811,
        1662933939.6459126
      ],
      [
        1770239087410,
        1662791932.9161465
      ],
      [
        1770242669050,
        1662944387.6912663
      ],
      [
        1770246267978,
        1663090149.3640432
      ],
      [
        1770249873350,
        1662983508.9331076
      ],
      [
        1770253461880,
        1662820244.1258495
      ],
      [
        1770257050719,
        1662807990.9668438
      ],
      [
        1770260645429,
        1663030819.451462
      ],
      [
        1770307428609,
        1660079556.2380884
      ],
      [
        1770311067423,
        1660008281.5619364
      ],
      [
        1770314693685,
        1660032981.6183002
      ],
      [
        1770318235558,
        1660016126.963262
      ],
      [
        1770321835648,
        1659886251.295908
      ],
      [
        1770325479985,
        1659891277.6075113
      ],
      [
        1770329055515,
        1659853417.058514
      ],
      [
        1770332684285,
        1659853417.058514
      ],
      [
        1770336261842,
        1659853417.058514
      ],
      [
        1770339834994,
        1660032595.3574393
      ],
      [
        1770343405097,
        1660199807.1174939
      ],
      [
        1770347049228,
        1660061569.7052584
      ],
      [
        1770350692646,
        1659882071.1124206
      ],
      [
        1770354244803,
        1659889139.9191227
      ],
      [
        1770357868569,
        1660093642.7606034
      ],
      [
        1770361598826,
        1660074268.5039074
      ],
      [
        1770365060818,
        1659929484.3532894
      ],
      [
        1770368627575,
        1659929484.3532894
      ],
      [
        1770415564999,
        1603076464.3770094
      ],
      [
        1770419035164,
        1603076464.3770094
      ],
      [
        1770422693822,
        1603073859.5046937
      ],
      [
        1770426270453,
        1603225603.585228
      ],
      [
        1770429861511,
        1603064176.0327117
      ],
      [
        1770433615705,
        1603217511.6559582
      ],
      [
        1770437036736,
        1603218252.8974848
      ],
      [
        1770440805143,
        1603218713.0656419
      ],
      [
        1770444441486,
        1603222784.6944587
      ],
      [
        1770447886454,
        1603227477.0727222
      ],
      [
        1770451494741,
        1603070013.7459638
      ],
      [
        1770455096175,
        1603070013.7459638
      ],
      [
        1770674904995,
        1579309733.5472128
      ],
      [
        1770678498005,
        1579309733.5472128
      ],
      [
        1770682109007,
        1579475551.9128006
      ],
      [
        1770685713364,
        1579322774.122163
      ],
      [
        1770689295853,
        1579341200.9817882
      ],
      [
        1770692878161,
        1579423621.2343607
      ],
      [
        1770696495942,
        1579475086.0259778
      ],
      [
        1770700127935,
        1579344946.7721026
      ],
      [
        1770703678014,
        1579339796.0822983
      ],
      [
        1772060633596,
        1811987013.595473
      ],
      [
        1772064341444,
        1811987482.0416913
      ],
      [
        1772067836744,
        1812165087.0726726
      ],
      [
        1772071471654,
        1811988517.7583404
      ],
      [
        1772075035913,
        1811812091.8371296
      ],
      [
        1772078619946,
        1812156867.489844
      ],
      [
        1772082265210,
        1811800184.8361573
      ],
      [
        1772085811884,
        1811985056.0583942
      ],
      [
        1772089469287,
        1811981401.097895
      ],
      [
        1772107478098,
        1811977994.2078743
      ],
      [
        1772111050173,
        1811825236.0586946
      ],
      [
        1772114728053,
        1811983761.8910785
      ],
      [
        1772118242891,
        1810508626.7366946
      ],
      [
        1772121838872,
        1810542767.3061614
      ],
      [
        1772125551137,
        1810542767.3061614
      ],
      [
        1772129062202,
        1810542767.3061614
      ],
      [
        1772132643980,
        1810542767.3061614
      ],
      [
        1772190262384,
        1810692849.0083282
      ],
      [
        1772193801836,
        1808279644.2669027
      ],
      [
        1772197455847,
        1808293036.0331063
      ],
      [
        1772201069388,
        1808290467.1026478
      ],
      [
        1772204773055,
        1883608610.854253
      ],
      [
        1772208246400,
        1883786823.1851661
      ],
      [
        1772211993288,
        1883613229.4925413
      ],
      [
        1772215446979,
        1883653996.5600367
      ],
      [
        1772219146262,
        1883638589.1029568
      ],
      [
        1772222642877,
        1883621952.062523
      ],
      [
        1772226303588,
        1883613149.0092165
      ],
      [
        1772229851179,
        1883790996.2125947
      ],
      [
        1772233427500,
        1883790996.2125947
      ],
      [
        1772237075012,
        1883790996.2125947
      ],
      [
        1772269492758,
        1883643162.3049932
      ],
      [
        1772273024465,
        1883613750.2343357
      ],
      [
        1772276668930,
        1883480721.5188847
      ],
      [
        1772280257923,
        1883628350.2411327
      ],
      [
        1772283826103,
        1883802150.0001419
      ],
      [
        1772287471078,
        1883592948.3505604
      ],
      [
        1772291037882,
        1883621061.6907673
      ],
      [
        1772294622193,
        1883793196.499353
      ],
      [
        1772298204221,
        1883793196.499353
      ],
      [
        1772301873903,
        1883793196.499353
      ],
      [
        1772305416770,
        1883793196.499353
      ],
      [
        1772306508000,
        1883793196.499353
      ],
      [
        1772309048901,
        1883793196.499353
      ]
    ],
    "total_volumes": [
      [
        1769774603404,
        668122.644
      ],
      [
        1769778286275,
        668188.2901373771
      ],
      [
        1769781873914,
        668121.8296814173
      ],
      [
        1769785497350,
        668149.4692439366
      ],
      [
        1769789046967,
        668696.9742816531
      ],
      [
        1769792638874,
        668684.7589050961
      ],
      [
        1769796284193,
        668689.9581571902
      ],
      [
        1769799861666,
        668767.4840928909
      ],
      [
        1769803453148,
        668747.0301110033
      ],
      [
        1769807052792,
        668752.2889278425
      ],
      [
        1769810645281,
        668755.3082301278
      ],
      [
        1769814262364,
        668746.265915
      ],
      [
        1769817890273,
        668688.4241674066
      ],
      [
        1769857469320,
        556.7849295027298
      ],
      [
        1769861099837,
        556.7341607013295
      ],
      [
        1769864667477,
        556.7878468050571
      ],
      [
        1769868255014,
        556.7850469142851
      ],
      [
        1769871974092,
        556.7885864082202
      ],
      [
        1769875463649,
        556.7891107065094
      ],
      [
        1769879054592,
        556.7891107065094
      ],
      [
        1769882746846,
        556.7891107065094
      ],
      [
        1769886276880,
        556.7891107065094
      ],
      [
        1770015894890,
        668.3213493660388
      ],
      [
        1770019687034,
        668.2573367232987
      ],
      [
        1770023081647,
        668.2593843035538
      ],
      [
        1770026676332,
        668.3179970413049
      ],
      [
        1770030269152,
        668.3187360416742
      ],
      [
        1770033885850,
        668.264000869156
      ],
      [
        1770037490351,
        668.3242513213659
      ],
      [
        1770041142246,
        668.3209648640038
      ],
      [
        1770044668788,
        668.2633903839367
      ],
      [
        1770131039068,
        668555.2866060795
      ],
      [
        1770134678413,
        668550.9272090807
      ],
      [
        1770138380251,
        668486.8917214351
      ],
      [
        1770141890524,
        668486.8917214351
      ],
      [
        1770145463602,
        668486.8917214351
      ],
      [
        1770149061629,
        779963.992798934
      ],
      [
        1770152753965,
        779890.9774512511
      ],
      [
        1770156263716,
        779819.8259192986
      ],
      [
        1770159995754,
        779968.8555967348
      ],
      [
        1770163492954,
        779964.9141649576
      ],
      [
        1770167073296,
        779967.3853326711
      ],
      [
        1770170669741,
        779920.4245834899
      ],
      [
        1770174341598,
        779836.9333418108
      ],
      [
        1770177857465,
        779898.6211978872
      ],
      [
        1770213880162,
        1225653.181762727
      ],
      [
        1770217442090,
        557214.0875428983
      ],
      [
        1770221048894,
        557116.8376882395
      ],
      [
        1770224798844,
        557109.4559612495
      ],
      [
        1770228148558,
        557111.6117027415
      ],
      [
        1770231747941,
        445652.4264142909
      ],
      [
        1770235479811,
        445691.78287452605
      ],
      [
        1770239087410,
        445653.7228944749
      ],
      [
        1770242669050,
        445694.5831108134
      ],
      [
        1770246267978,
        445733.64947314217
      ],
      [
        1770249873350,
        445741.338541293
      ],
      [
        1770253461880,
        445710.3705679925
      ],
      [
        1770257050719,
        445658.02669817634
      ],
      [
        1770260645429,
        445717.7481472471
      ],
      [
        1770307428609,
        2115.316279190735
      ],
      [
        1770311067423,
        2115.2254591561227
      ],
      [
        1770314693685,
        2115.090662931856
      ],
      [
        1770318235558,
        2115.2354559692753
      ],
      [
        1770321835648,
        2115.0699650369925
      ],
      [
        1770325479985,
        2115.0763696931544
      ],
      [
        1770329055515,
        2115.028126803027
      ],
      [
        1770332684285,
        2115.028126803027
      ],
      [
        1770336261842,
        2115.028126803027
      ],
      [
        1770339834994,
        2655.772443375937
      ],
      [
        1770343405097,
        2656.039954017477
      ],
      [
        1770347049228,
        2655.81879745038
      ],
      [
        1770350692646,
        2655.5216315807133
      ],
      [
        1770354244803,
        2655.5429388463276
      ],
      [
        1770357868569,
        2655.6415785555114
      ],
      [
        1770361598826,
        2655.839113388519
      ],
      [
        1770365060818,
        2655.6074831431106
      ],
      [
        1770368627575,
        2655.6074831431106
      ],
      [
        1770415564999,
        557731.305633158
      ],
      [
        1770419035164,
        557731.305633158
      ],
      [
        1770422693822,
        557730.2436442897
      ],
      [
        1770426270453,
        557242.6192820247
      ],
      [
        1770429861511,
        557243.6680771768
      ],
      [
        1770433615705,
        557187.8842586932
      ],
      [
        1770437036736,
        557241.7844354431
      ],
      [
        1770440805143,
        557240.2243033181
      ],
      [
        1770444441486,
        557241.6789857378
      ],
      [
        1770447886454,
        557243.2704611705
      ],
      [
        1770451494741,
        557188.54
      ],
      [
        1770455096175,
        557188.54
      ],
      [
        1770674904995,
        44.59945521501797
      ],
      [
        1770678498005,
        44.59945521501797
      ],
      [
        1770682109007,
        44.59935886548593
      ],
      [
        1770685713364,
        44.59982347877656
      ],
      [
        1770689295853,
        44.60023699618484
      ],
      [
        1770692878161,
        44.60267138515522
      ],
      [
        1770696495942,
        44.60048890072421
      ],
      [
        1770700127935,
        44.60044963087771
      ],
      [
        1770703678014,
        44.600304176218366
      ],
      [
        1772060633596,
        558916.7341138076
      ],
      [
        1772064341444,
        558916.8786084579
      ],
      [
        1772067836744,
        558971.661795718
      ],
      [
        1772071471654,
        558917.2101160334
      ],
      [
        1772075035913,
        558862.7785958236
      ],
      [
        1772078619946,
        558969.1264230272
      ],
      [
        1772082265210,
        558859.1058199999
      ],
      [
        1772085811884,
        558970.9
      ],
      [
        1772089469287,
        558915.0029099999
      ],
      [
        1772107478098,
        223578.11953730963
      ],
      [
        1772111050173,
        223559.27086483868
      ],
      [
        1772114728053,
        223578.8312058669
      ],
      [
        1772118242891,
        223595.85245504536
      ],
      [
        1772121838872,
        223600.0687783595
      ],
      [
        1772125551137,
        223600.0687783595
      ],
      [
        1772129062202,
        223600.0687783595
      ],
      [
        1772132643980,
        223600.0687783595
      ],
      [
        1772190262384,
        223637.70521811044
      ],
      [
        1772193801836,
        335312.88094402
      ],
      [
        1772197455847,
        335315.36420578806
      ],
      [
        1772201069388,
        335314.88784391794
      ],
      [
        1772204773055,
        335340.65810419776
      ],
      [
        1772208246400,
        447032.0010166038
      ],
      [
        1772211993288,
        447030.80111634225
      ],
      [
        1772215446979,
        447000.48059651756
      ],
      [
        1772219146262,
        446996.82433016936
      ],
      [
        1772222642877,
        447025.81458579475
      ],
      [
        1772226303588,
        446990.78726914356
      ],
      [
        1772229851179,
        447032.9912968088
      ],
      [
        1772233427500,
        447032.9912968088
      ],
      [
        1772237075012,
        447032.9912968088
      ],
      [
        1772269492758,
        223375.6801831764
      ],
      [
        1772273024465,
        223372.19229257153
      ],
      [
        1772276668930,
        223356.41681004257
      ],
      [
        1772280257923,
        111680.24681856258
      ],
      [
        1772283826103,
        111680.86427302506
      ],
      [
        1772287471078,
        111678.14784193781
      ],
      [
        1772291037882,
        111679.81468071358
      ],
      [
        1772294622193,
        111690.02054638049
      ],
      [
        1772298204221,
        111690.02054638049
      ],
      [
        1772301873903,
        111690.02054638049
      ],
      [
        1772305416770,
        111690.02054638049
      ],
      [
        1772306508000,
        111690.02054638049
      ],
      [
        1772309048901,
        111690.02054638049
      ]
    ]
  }
}