{
  "savedAt": "2026-03-30T05:56:30.090Z",
  "id": "usda-2",
  "detail": {
    "id": "usda-2",
    "symbol": "usda",
    "name": "USDa",
    "web_slug": "usda",
    "asset_platform_id": "ethereum",
    "platforms": {
      "ethereum": "0x8a60e489004ca22d775c5f2c657598278d17d9c2",
      "mantle": "0x075df695b8e7f4361fa7f8c1426c63f11b06e326",
      "binance-smart-chain": "0x9356086146be5158e98ad827e21b5cf944699894"
    },
    "detail_platforms": {
      "ethereum": {
        "decimal_place": 18,
        "contract_address": "0x8a60e489004ca22d775c5f2c657598278d17d9c2",
        "geckoterminal_url": "https://www.geckoterminal.com/eth/tokens/0x8a60e489004ca22d775c5f2c657598278d17d9c2"
      },
      "mantle": {
        "decimal_place": 18,
        "contract_address": "0x075df695b8e7f4361fa7f8c1426c63f11b06e326",
        "geckoterminal_url": "https://www.geckoterminal.com/mantle/tokens/0x075df695b8e7f4361fa7f8c1426c63f11b06e326"
      },
      "binance-smart-chain": {
        "decimal_place": 18,
        "contract_address": "0x9356086146be5158e98ad827e21b5cf944699894",
        "geckoterminal_url": "https://www.geckoterminal.com/bsc/tokens/0x9356086146be5158e98ad827e21b5cf944699894"
      }
    },
    "block_time_in_minutes": 0,
    "hashing_algorithm": null,
    "categories": [
      "Stablecoins",
      "Ethereum Ecosystem"
    ],
    "preview_listing": false,
    "public_notice": null,
    "additional_notices": [],
    "description": {
      "en": "Avalon Labs is creating an on-chain financial center for Bitcoin, offering BTC-backed\nlending, a Bitcoin-backed stablecoin, yield accounts, and a credit card. The goal is to\nmake Bitcoin an active economic asset in global markets through a scalable and\naccessible network.\nUSDa is the flagship CDP (Collateralized Debt Position) product based on Avalon's CeDeFi\nlending platform. The goal of USDa is to provide the best stablecoin solution for DeFi\ncommunity with extremely high capital efficiency, stability and deep liquidity from BTC\ncommunity."
    },
    "links": {
      "homepage": [
        "https://www.avalonfinance.xyz/",
        "https://usda.avalonfinance.xyz/"
      ],
      "whitepaper": "",
      "blockchain_site": [
        "https://etherscan.io/token/0x8A60E489004Ca22d775C5F2c657598278d17D9c2",
        "https://intel.arkm.com/explorer/token/usda-2 ",
        "https://bscscan.com/token/0x9356086146be5158E98aD827E21b5cF944699894",
        "https://ethplorer.io/address/0x8A60E489004Ca22d775C5F2c657598278d17D9c2",
        "https://binplorer.com/address/0x9356086146be5158e98ad827e21b5cf944699894",
        "https://mantlescan.xyz/token/0x075df695b8e7f4361fa7f8c1426c63f11b06e326",
        "https://intel.arkm.com/explorer/token/usda-2"
      ],
      "official_forum_url": [],
      "chat_url": [
        "https://discord.com/invite/avalonlabs",
        "https://medium.com/@avalonlabs"
      ],
      "announcement_url": [],
      "snapshot_url": null,
      "twitter_screen_name": "avalonfinance_",
      "facebook_username": null,
      "bitcointalk_thread_identifier": null,
      "telegram_channel_identifier": "AvalonLabs_Official",
      "subreddit_url": null,
      "repos_url": {
        "github": [
          "https://github.com/avalonfinancexyz"
        ],
        "bitbucket": []
      }
    },
    "image": {
      "thumb": "https://coin-images.coingecko.com/coins/images/51599/thumb/SUSDA.png?1731604761",
      "small": "https://coin-images.coingecko.com/coins/images/51599/small/SUSDA.png?1731604761",
      "large": "https://coin-images.coingecko.com/coins/images/51599/large/SUSDA.png?1731604761"
    },
    "country_origin": null,
    "genesis_date": null,
    "contract_address": "0x8a60e489004ca22d775c5f2c657598278d17d9c2",
    "sentiment_votes_up_percentage": null,
    "sentiment_votes_down_percentage": null,
    "watchlist_portfolio_users": 256,
    "market_cap_rank": 156,
    "market_cap_rank_with_rehypothecated": 221,
    "market_data": {
      "current_price": {
        "aed": 3.63,
        "ars": 1369.86,
        "aud": 1.44,
        "bch": 0.00217154,
        "bdt": 121.18,
        "bhd": 0.372293,
        "bmd": 0.987646,
        "bnb": 0.00160016,
        "brl": 5.18,
        "btc": 0.00001464,
        "cad": 1.37,
        "chf": 0.788502,
        "clp": 914.49,
        "cny": 6.82,
        "czk": 21.03,
        "dkk": 6.41,
        "dot": 0.77522336,
        "eos": 13.354416,
        "eth": 0.00048225,
        "eur": 0.857403,
        "gbp": 0.743968,
        "gel": 2.65,
        "hkd": 7.74,
        "huf": 334.24,
        "idr": 16772.39,
        "ils": 3.1,
        "inr": 92.68,
        "jpy": 157.74,
        "krw": 1493.98,
        "kwd": 0.304106,
        "lkr": 311.11,
        "ltc": 0.01824957,
        "mmk": 2073.87,
        "mxn": 17.85,
        "myr": 3.97,
        "ngn": 1365.1,
        "nok": 9.62,
        "nzd": 1.72,
        "php": 59.95,
        "pkr": 275.64,
        "pln": 3.67,
        "rub": 80.47,
        "sar": 3.71,
        "sek": 9.34,
        "sgd": 1.27,
        "sol": 0.01181841,
        "thb": 32.39,
        "try": 43.92,
        "twd": 31.59,
        "uah": 43.29,
        "usd": 0.987646,
        "vef": 0.098893,
        "vnd": 26011,
        "xag": 0.01409671,
        "xau": 0.00021993,
        "xdr": 0.700232,
        "xlm": 5.836426,
        "xrp": 0.72905356,
        "yfi": 0.00040117,
        "zar": 16.89,
        "bits": 14.64,
        "link": 0.11391757,
        "sats": 1463.88
      },
      "total_value_locked": null,
      "mcap_to_tvl_ratio": null,
      "fdv_to_tvl_ratio": null,
      "roi": null,
      "ath": {
        "aed": 3.75,
        "ars": 1482.92,
        "aud": 1.68,
        "bch": 0.0039776,
        "bdt": 124.27,
        "bhd": 0.384894,
        "bmd": 1.021,
        "bnb": 0.00194076,
        "brl": 6.75,
        "btc": 0.00001576,
        "cad": 1.48,
        "chf": 0.938295,
        "clp": 1035.89,
        "cny": 7.49,
        "czk": 25.25,
        "dkk": 7.47,
        "dot": 0.80342305,
        "eos": 13.989922,
        "eth": 0.00071333,
        "eur": 1.001,
        "gbp": 0.840752,
        "gel": 2.9,
        "hkd": 7.95,
        "huf": 414.05,
        "idr": 17282.75,
        "ils": 3.82,
        "inr": 93.78,
        "jpy": 160.77,
        "krw": 1499.38,
        "kwd": 0.314107,
        "lkr": 311.25,
        "ltc": 0.01959539,
        "mmk": 2143.05,
        "mxn": 21.3,
        "myr": 4.61,
        "ngn": 1705,
        "nok": 11.73,
        "nzd": 1.84,
        "php": 60.07,
        "pkr": 292.14,
        "pln": 4.28,
        "rub": 114.79,
        "sar": 3.83,
        "sek": 11.54,
        "sgd": 1.4,
        "sol": 0.0129838,
        "thb": 35.53,
        "try": 43.94,
        "twd": 33.79,
        "uah": 43.55,
        "usd": 1.021,
        "vef": 0.10228,
        "vnd": 26668,
        "xag": 0.03493102,
        "xau": 0.0003918,
        "xdr": 0.787643,
        "xlm": 7.900912,
        "xrp": 1.345342,
        "yfi": 0.00041558,
        "zar": 19.85,
        "bits": 15.76,
        "link": 0.12224119,
        "sats": 1576.11
      },
      "ath_change_percentage": {
        "aed": -3.32544,
        "ars": -7.62408,
        "aud": -14.62273,
        "bch": -45.40575,
        "bdt": -2.48724,
        "bhd": -3.27377,
        "bmd": -3.31175,
        "bnb": -17.54944,
        "brl": -23.28986,
        "btc": -7.12035,
        "cad": -7.4806,
        "chf": -15.96438,
        "clp": -11.71948,
        "cny": -8.90939,
        "czk": -16.72138,
        "dkk": -14.22255,
        "dot": -3.50994,
        "eos": -4.54259,
        "eth": -32.39515,
        "eur": -14.35759,
        "gbp": -11.51152,
        "gel": -8.62223,
        "hkd": -2.72861,
        "huf": -19.27621,
        "idr": -2.95298,
        "ils": -18.7846,
        "inr": -1.16942,
        "jpy": -1.88611,
        "krw": -0.36004,
        "kwd": -3.18378,
        "lkr": -0.04543,
        "ltc": -6.86804,
        "mmk": -3.22833,
        "mxn": -16.20146,
        "myr": -13.78452,
        "ngn": -19.93543,
        "nok": -18.03762,
        "nzd": -6.46449,
        "php": -0.19738,
        "pkr": -5.64878,
        "pln": -14.19012,
        "rub": -29.8969,
        "sar": -3.3494,
        "sek": -19.06761,
        "sgd": -9.36739,
        "sol": -8.97569,
        "thb": -8.81799,
        "try": -0.05,
        "twd": -6.49742,
        "uah": -0.59443,
        "usd": -3.31175,
        "vef": -3.31175,
        "vnd": -2.46389,
        "xag": -59.64416,
        "xau": -43.86761,
        "xdr": -11.09775,
        "xlm": -26.12972,
        "xrp": -45.80904,
        "yfi": -3.46747,
        "zar": -14.91764,
        "bits": -7.12035,
        "link": -6.80917,
        "sats": -7.12035
      },
      "ath_date": {
        "aed": "2025-01-13T15:25:59.380Z",
        "ars": "2025-10-27T14:22:22.156Z",
        "aud": "2025-04-09T00:21:33.188Z",
        "bch": "2025-04-07T07:01:11.438Z",
        "bdt": "2025-02-02T22:45:41.626Z",
        "bhd": "2025-01-13T15:25:59.380Z",
        "bmd": "2025-01-13T15:25:59.380Z",
        "bnb": "2025-03-11T01:11:06.600Z",
        "brl": "2024-12-26T11:21:03.347Z",
        "btc": "2026-02-24T13:35:04.191Z",
        "cad": "2025-02-03T14:35:45.881Z",
        "chf": "2025-01-13T15:25:59.380Z",
        "clp": "2025-01-13T15:25:59.380Z",
        "cny": "2025-01-13T15:25:59.380Z",
        "czk": "2025-01-13T15:25:59.380Z",
        "dkk": "2025-01-13T15:25:59.380Z",
        "dot": "2026-02-11T15:15:13.138Z",
        "eos": "2026-03-29T23:10:29.632Z",
        "eth": "2025-04-09T01:31:31.482Z",
        "eur": "2025-01-13T15:25:59.380Z",
        "gbp": "2025-01-13T15:25:59.380Z",
        "gel": "2025-01-29T19:41:16.588Z",
        "hkd": "2025-01-13T15:25:59.380Z",
        "huf": "2025-01-13T15:25:59.380Z",
        "idr": "2025-04-07T02:46:42.684Z",
        "ils": "2025-04-10T02:15:38.180Z",
        "inr": "2026-03-29T14:45:37.722Z",
        "jpy": "2025-01-13T15:25:59.380Z",
        "krw": "2025-01-13T15:25:59.380Z",
        "kwd": "2025-01-13T15:25:59.380Z",
        "lkr": "2026-03-28T13:05:17.340Z",
        "ltc": "2026-02-24T06:00:06.468Z",
        "mmk": "2025-01-13T15:25:59.380Z",
        "mxn": "2025-02-03T01:59:55.318Z",
        "myr": "2025-01-13T15:25:59.380Z",
        "ngn": "2024-11-24T00:06:02.585Z",
        "nok": "2025-01-13T15:25:59.380Z",
        "nzd": "2025-01-13T15:25:59.380Z",
        "php": "2026-03-30T01:25:38.541Z",
        "pkr": "2025-03-10T23:01:06.576Z",
        "pln": "2025-01-13T15:25:59.380Z",
        "rub": "2024-11-27T13:31:07.014Z",
        "sar": "2025-01-13T15:25:59.380Z",
        "sek": "2025-01-13T15:25:59.380Z",
        "sgd": "2025-01-13T15:25:59.380Z",
        "sol": "2026-02-24T14:40:04.127Z",
        "thb": "2025-01-13T15:25:59.380Z",
        "try": "2026-03-29T14:45:37.722Z",
        "twd": "2025-01-13T15:25:59.380Z",
        "uah": "2026-03-19T02:40:11.325Z",
        "usd": "2025-01-13T15:25:59.380Z",
        "vef": "2025-01-13T15:25:59.380Z",
        "vnd": "2025-10-10T20:10:49.873Z",
        "xag": "2024-12-19T20:00:42.141Z",
        "xau": "2024-11-15T20:41:30.275Z",
        "xdr": "2025-01-13T15:25:59.380Z",
        "xlm": "2024-11-14T17:25:25.061Z",
        "xrp": "2024-11-14T17:25:25.061Z",
        "yfi": "2026-03-29T01:40:54.932Z",
        "zar": "2025-04-09T15:01:12.128Z",
        "bits": "2026-02-24T13:35:04.191Z",
        "link": "2026-02-24T14:34:57.021Z",
        "sats": "2026-02-24T13:35:04.191Z"
      },
      "atl": {
        "aed": 2.71,
        "ars": 746.8,
        "aud": 1.15,
        "bch": 0.00122352,
        "bdt": 87.9,
        "bhd": 0.278166,
        "bmd": 0.737813,
        "bnb": 0.00070162,
        "brl": 4.29,
        "btc": 0.00000716,
        "cad": 1.036,
        "chf": 0.621488,
        "clp": 716.32,
        "cny": 5.36,
        "czk": 16.27,
        "dkk": 5,
        "dot": 0.06975868,
        "eos": 0.54954035,
        "eth": 0.00019011,
        "eur": 0.66917,
        "gbp": 0.578126,
        "gel": 2.1,
        "hkd": 5.74,
        "huf": 262.83,
        "idr": 11690.09,
        "ils": 2.54,
        "inr": 62.48,
        "jpy": 111.07,
        "krw": 1047.33,
        "kwd": 0.226806,
        "lkr": 214.33,
        "ltc": 0.00541205,
        "mmk": 1547.93,
        "mxn": 14.46,
        "myr": 3.26,
        "ngn": 1137.82,
        "nok": 7.87,
        "nzd": 1.26,
        "php": 42.73,
        "pkr": 204.98,
        "pln": 2.85,
        "rub": 63.19,
        "sar": 2.77,
        "sek": 7.39,
        "sgd": 0.988302,
        "sol": 0.00397739,
        "thb": 25.14,
        "try": 25.67,
        "twd": 23.89,
        "uah": 30.58,
        "usd": 0.737813,
        "vef": 0.073877,
        "vnd": 18728.59,
        "xag": 0.00808071,
        "xau": 0.0001772,
        "xdr": 0.546366,
        "xlm": 1.566615,
        "xrp": 0.26907227,
        "yfi": 0.00005717,
        "zar": 13.31,
        "bits": 7.16,
        "link": 0.03133046,
        "sats": 715.65
      },
      "atl_change_percentage": {
        "aed": 33.84409,
        "ars": 83.42936,
        "aud": 25.22526,
        "bch": 77.48315,
        "bdt": 37.86424,
        "bhd": 33.83868,
        "bmd": 33.8614,
        "bnb": 128.06869,
        "brl": 20.72808,
        "btc": 104.55353,
        "cad": 32.44449,
        "chf": 26.87322,
        "clp": 27.66412,
        "cny": 27.30092,
        "czk": 29.23181,
        "dkk": 28.24644,
        "dot": 1011.29298,
        "eos": 2330.10657,
        "eth": 153.67104,
        "eur": 28.1294,
        "gbp": 28.68627,
        "gel": 26.31992,
        "hkd": 34.77852,
        "huf": 27.16912,
        "idr": 43.47537,
        "ils": 21.76569,
        "inr": 48.3387,
        "jpy": 42.01824,
        "krw": 42.64668,
        "kwd": 34.08218,
        "lkr": 45.15097,
        "ltc": 237.20231,
        "mmk": 33.97689,
        "mxn": 23.47161,
        "myr": 21.80646,
        "ngn": 19.97508,
        "nok": 22.16258,
        "nzd": 36.51262,
        "php": 40.32101,
        "pkr": 34.46906,
        "pln": 28.70368,
        "rub": 27.34198,
        "sar": 33.7194,
        "sek": 26.271,
        "sgd": 28.65456,
        "sol": 197.14009,
        "thb": 28.88029,
        "try": 71.06293,
        "twd": 32.26029,
        "uah": 41.5479,
        "usd": 33.8614,
        "vef": 33.8614,
        "vnd": 38.88515,
        "xag": 74.4488,
        "xau": 24.11118,
        "xdr": 28.16174,
        "xlm": 272.55019,
        "xrp": 170.95084,
        "yfi": 601.74861,
        "zar": 26.91251,
        "bits": 104.55353,
        "link": 263.60009,
        "sats": 104.55353
      },
      "atl_date": {
        "aed": "2024-12-06T09:52:06.910Z",
        "ars": "2024-12-06T09:52:06.910Z",
        "aud": "2024-12-06T09:52:06.910Z",
        "bch": "2024-12-06T16:40:32.381Z",
        "bdt": "2024-12-06T09:52:06.910Z",
        "bhd": "2024-12-06T09:52:06.910Z",
        "bmd": "2024-12-06T09:52:06.910Z",
        "bnb": "2025-10-16T03:11:03.522Z",
        "brl": "2025-10-10T21:20:39.330Z",
        "btc": "2025-10-10T21:20:39.330Z",
        "cad": "2024-12-06T09:52:06.910Z",
        "chf": "2025-10-10T21:20:39.330Z",
        "clp": "2024-12-06T09:52:06.910Z",
        "cny": "2024-12-06T09:52:06.910Z",
        "czk": "2025-10-10T21:20:39.330Z",
        "dkk": "2025-10-10T21:20:39.330Z",
        "dot": "2024-12-05T19:55:38.700Z",
        "eos": "2024-12-06T07:25:32.559Z",
        "eth": "2024-12-06T09:52:06.910Z",
        "eur": "2025-10-10T21:20:39.330Z",
        "gbp": "2024-12-06T09:52:06.910Z",
        "gel": "2024-12-06T09:52:06.910Z",
        "hkd": "2024-12-06T09:52:06.910Z",
        "huf": "2025-10-10T21:20:39.330Z",
        "idr": "2024-12-06T09:52:06.910Z",
        "ils": "2025-10-10T21:20:39.330Z",
        "inr": "2024-12-06T09:52:06.910Z",
        "jpy": "2024-12-06T09:52:06.910Z",
        "krw": "2024-12-06T09:52:06.910Z",
        "kwd": "2024-12-06T09:52:06.910Z",
        "lkr": "2024-12-06T09:52:06.910Z",
        "ltc": "2024-12-05T19:55:38.700Z",
        "mmk": "2024-12-06T09:52:06.910Z",
        "mxn": "2025-10-10T21:20:39.330Z",
        "myr": "2024-12-06T09:52:06.910Z",
        "ngn": "2025-10-10T21:20:39.330Z",
        "nok": "2025-10-10T21:20:39.330Z",
        "nzd": "2024-12-06T09:52:06.910Z",
        "php": "2024-12-06T09:52:06.910Z",
        "pkr": "2024-12-06T09:52:06.910Z",
        "pln": "2025-10-10T21:20:39.330Z",
        "rub": "2025-10-10T21:20:39.330Z",
        "sar": "2024-12-06T09:52:06.910Z",
        "sek": "2025-10-10T21:20:39.330Z",
        "sgd": "2024-12-06T09:52:06.910Z",
        "sol": "2025-09-14T03:08:29.518Z",
        "thb": "2024-12-06T09:52:06.910Z",
        "try": "2024-12-06T09:52:06.910Z",
        "twd": "2025-10-10T21:20:39.330Z",
        "uah": "2024-12-06T09:52:06.910Z",
        "usd": "2024-12-06T09:52:06.910Z",
        "vef": "2024-12-06T09:52:06.910Z",
        "vnd": "2024-12-06T09:52:06.910Z",
        "xag": "2026-01-29T14:21:12.989Z",
        "xau": "2026-01-29T14:31:02.703Z",
        "xdr": "2025-10-10T21:20:39.330Z",
        "xlm": "2024-12-06T06:55:33.636Z",
        "xrp": "2025-07-18T01:02:55.844Z",
        "yfi": "2024-12-06T16:40:32.381Z",
        "zar": "2024-12-06T09:52:06.910Z",
        "bits": "2025-10-10T21:20:39.330Z",
        "link": "2024-12-06T09:52:06.910Z",
        "sats": "2025-10-10T21:20:39.330Z"
      },
      "market_cap": {
        "aed": 800499942,
        "ars": 302325014543,
        "aud": 317224667,
        "bch": 479254,
        "bdt": 26744493576,
        "bhd": 82164317,
        "bmd": 217971393,
        "bnb": 353153,
        "brl": 1143281754,
        "btc": 3231,
        "cad": 302767279,
        "chf": 174020731,
        "clp": 201825364092,
        "cny": 1505724587,
        "czk": 4640959716,
        "dkk": 1413984351,
        "dot": 171090110,
        "eos": 2947290635,
        "eth": 106431,
        "eur": 189227070,
        "gbp": 164192183,
        "gel": 584163334,
        "hkd": 1707424416,
        "huf": 73766183612,
        "idr": 3701630835988,
        "ils": 683917942,
        "inr": 20454947553,
        "jpy": 34813242939,
        "krw": 329717674612,
        "kwd": 67115572,
        "lkr": 68660315327,
        "ltc": 4027641,
        "mmk": 457698511160,
        "mxn": 3940040005,
        "myr": 876571958,
        "ngn": 301275700257,
        "nok": 2122266917,
        "nzd": 379780059,
        "php": 13231844221,
        "pkr": 60832801734,
        "pln": 810330015,
        "rub": 17759678527,
        "sar": 817937653,
        "sek": 2060786342,
        "sgd": 280616372,
        "sol": 2608298,
        "thb": 7149316310,
        "try": 9692272158,
        "twd": 6972643085,
        "uah": 9553965603,
        "usd": 217971393,
        "vef": 21825476,
        "vnd": 5740621364360,
        "xag": 3111112,
        "xau": 48538,
        "xdr": 154539756,
        "xlm": 1288086566,
        "xrp": 160900537,
        "yfi": 88538,
        "zar": 3726649499,
        "bits": 3230756270,
        "link": 25141361,
        "sats": 323075627048
      },
      "market_cap_rank": 156,
      "outstanding_token_value_usd": null,
      "market_cap_rank_with_rehypothecated": 221,
      "fully_diluted_valuation": {
        "aed": 800499942,
        "ars": 302325014543,
        "aud": 317224667,
        "bch": 479254,
        "bdt": 26744493576,
        "bhd": 82164317,
        "bmd": 217971393,
        "bnb": 353153,
        "brl": 1143281754,
        "btc": 3231,
        "cad": 302767279,
        "chf": 174020731,
        "clp": 201825364092,
        "cny": 1505724587,
        "czk": 4640959716,
        "dkk": 1413984351,
        "dot": 171090110,
        "eos": 2947290635,
        "eth": 106431,
        "eur": 189227070,
        "gbp": 164192183,
        "gel": 584163334,
        "hkd": 1707424416,
        "huf": 73766183612,
        "idr": 3701630835988,
        "ils": 683917942,
        "inr": 20454947553,
        "jpy": 34813242939,
        "krw": 329717674612,
        "kwd": 67115572,
        "lkr": 68660315327,
        "ltc": 4027641,
        "mmk": 457698511160,
        "mxn": 3940040005,
        "myr": 876571958,
        "ngn": 301275700257,
        "nok": 2122266917,
        "nzd": 379780059,
        "php": 13231844221,
        "pkr": 60832801734,
        "pln": 810330015,
        "rub": 17759678527,
        "sar": 817937653,
        "sek": 2060786342,
        "sgd": 280616372,
        "sol": 2608298,
        "thb": 7149316310,
        "try": 9692272158,
        "twd": 6972643085,
        "uah": 9553965603,
        "usd": 217971393,
        "vef": 21825476,
        "vnd": 5740621364360,
        "xag": 3111112,
        "xau": 48538,
        "xdr": 154539756,
        "xlm": 1288086566,
        "xrp": 160900537,
        "yfi": 88538,
        "zar": 3726649499,
        "bits": 3230756270,
        "link": 25141361,
        "sats": 323075627048
      },
      "market_cap_fdv_ratio": 1,
      "total_volume": {
        "aed": 7.49,
        "ars": 2828.58,
        "aud": 2.97,
        "bch": 0.00448395,
        "bdt": 250.22,
        "bhd": 0.768738,
        "bmd": 2.04,
        "bnb": 0.00330413,
        "brl": 10.7,
        "btc": 0.00003023,
        "cad": 2.83,
        "chf": 1.63,
        "clp": 1888.3,
        "cny": 14.09,
        "czk": 43.42,
        "dkk": 13.23,
        "dot": 1.600736,
        "eos": 27.575148,
        "eth": 0.00099578,
        "eur": 1.77,
        "gbp": 1.54,
        "gel": 5.47,
        "hkd": 15.97,
        "huf": 690.16,
        "idr": 34633,
        "ils": 6.4,
        "inr": 191.38,
        "jpy": 325.72,
        "krw": 3084.87,
        "kwd": 0.62794,
        "lkr": 642.39,
        "ltc": 0.03768301,
        "mmk": 4282.27,
        "mxn": 36.86,
        "myr": 8.2,
        "ngn": 2818.77,
        "nok": 19.86,
        "nzd": 3.55,
        "php": 123.8,
        "pkr": 569.16,
        "pln": 7.58,
        "rub": 166.16,
        "sar": 7.65,
        "sek": 19.28,
        "sgd": 2.63,
        "sol": 0.0244035,
        "thb": 66.89,
        "try": 90.68,
        "twd": 65.24,
        "uah": 89.39,
        "usd": 2.04,
        "vef": 0.204201,
        "vnd": 53710,
        "xag": 0.02910788,
        "xau": 0.00045413,
        "xdr": 1.45,
        "xlm": 12.051468,
        "xrp": 1.505402,
        "yfi": 0.00082837,
        "zar": 34.87,
        "bits": 30.23,
        "link": 0.2352251,
        "sats": 3022.73
      },
      "high_24h": {
        "aed": 3.63,
        "ars": 1373.81,
        "aud": 1.44,
        "bch": 0.00219959,
        "bdt": 121.19,
        "bhd": 0.372417,
        "bmd": 0.988714,
        "bnb": 0.00165152,
        "brl": 5.2,
        "btc": 0.00001519,
        "cad": 1.37,
        "chf": 0.790207,
        "clp": 915.48,
        "cny": 6.84,
        "czk": 21.13,
        "dkk": 6.42,
        "dot": 0.8003078,
        "eos": 13.989922,
        "eth": 0.00050817,
        "eur": 0.859772,
        "gbp": 0.746229,
        "gel": 2.65,
        "hkd": 7.74,
        "huf": 335.36,
        "idr": 16799.04,
        "ils": 3.1,
        "inr": 93.78,
        "jpy": 158.49,
        "krw": 1495.44,
        "kwd": 0.304137,
        "lkr": 311.14,
        "ltc": 0.018713,
        "mmk": 2076.11,
        "mxn": 17.94,
        "myr": 3.97,
        "ngn": 1365.11,
        "nok": 9.64,
        "nzd": 1.73,
        "php": 60.07,
        "pkr": 275.67,
        "pln": 3.68,
        "rub": 80.7,
        "sar": 3.71,
        "sek": 9.37,
        "sgd": 1.28,
        "sol": 0.01237688,
        "thb": 32.59,
        "try": 43.94,
        "twd": 31.68,
        "uah": 43.29,
        "usd": 0.988714,
        "vef": 0.099,
        "vnd": 26040,
        "xag": 0.01454353,
        "xau": 0.00022312,
        "xdr": 0.700303,
        "xlm": 6.096092,
        "xrp": 0.75727505,
        "yfi": 0.00041421,
        "zar": 16.97,
        "bits": 15.19,
        "link": 0.11933066,
        "sats": 1519.2
      },
      "low_24h": {
        "aed": 3.61,
        "ars": 1360.43,
        "aud": 1.43,
        "bch": 0.00203146,
        "bdt": 120.09,
        "bhd": 0.369782,
        "bmd": 0.981903,
        "bnb": 0.00159907,
        "brl": 5.16,
        "btc": 0.00001464,
        "cad": 1.36,
        "chf": 0.781645,
        "clp": 909.17,
        "cny": 6.79,
        "czk": 20.92,
        "dkk": 6.38,
        "dot": 0.77177148,
        "eos": 12.93035,
        "eth": 0.00048225,
        "eur": 0.850611,
        "gbp": 0.737818,
        "gel": 2.63,
        "hkd": 7.68,
        "huf": 331.3,
        "idr": 16683.33,
        "ils": 3.08,
        "inr": 91.81,
        "jpy": 157.39,
        "krw": 1480.71,
        "kwd": 0.302017,
        "lkr": 308.29,
        "ltc": 0.01812134,
        "mmk": 2061.81,
        "mxn": 17.79,
        "myr": 3.89,
        "ngn": 1353.09,
        "nok": 9.54,
        "nzd": 1.71,
        "php": 59.31,
        "pkr": 273.15,
        "pln": 3.65,
        "rub": 79.93,
        "sar": 3.68,
        "sek": 9.3,
        "sgd": 1.27,
        "sol": 0.01181841,
        "thb": 32.18,
        "try": 43.64,
        "twd": 31.46,
        "uah": 42.9,
        "usd": 0.981903,
        "vef": 0.098318,
        "vnd": 25861,
        "xag": 0.01404991,
        "xau": 0.0002185,
        "xdr": 0.693809,
        "xlm": 5.831962,
        "xrp": 0.7285897,
        "yfi": 0.00040117,
        "zar": 16.81,
        "bits": 14.64,
        "link": 0.11391757,
        "sats": 1463.88
      },
      "price_change_24h": 0.00574282,
      "price_change_percentage_24h": 0.58487,
      "price_change_percentage_7d": 0.36909,
      "price_change_percentage_14d": 0.36174,
      "price_change_percentage_30d": 0.36836,
      "price_change_percentage_60d": 0.52545,
      "price_change_percentage_200d": -0.3419,
      "price_change_percentage_1y": -1.29384,
      "market_cap_change_24h": -25861.2521753,
      "market_cap_change_percentage_24h": -0.01186,
      "price_change_24h_in_currency": {
        "aed": 0.0210905,
        "ars": 9.43,
        "aud": 0.01101484,
        "bch": 0.00014008,
        "bdt": 1.096,
        "bhd": 0.00251137,
        "bmd": 0.00574282,
        "bnb": 0.00000109,
        "brl": 0.02040081,
        "btc": -6.3875954356e-8,
        "cad": 0.00696849,
        "chf": 0.00442972,
        "clp": 5.32,
        "cny": 0.0357432,
        "czk": 0.104894,
        "dkk": 0.03167459,
        "dot": 0.00345188,
        "eos": 0.19828276,
        "eth": -0.000007705411832757,
        "eur": 0.0067922,
        "gbp": 0.00385853,
        "gel": 0.00557172,
        "hkd": 0.051956,
        "huf": 2.34,
        "idr": 89.07,
        "ils": 0.01790113,
        "inr": -0.45069279563159625,
        "jpy": 0.355302,
        "krw": 13.27,
        "kwd": 0.00208935,
        "lkr": 2.81,
        "ltc": 0.00012824,
        "mmk": 12.06,
        "mxn": 0.058492,
        "myr": 0.03094997,
        "ngn": 12.02,
        "nok": 0.04792098,
        "nzd": 0.01211605,
        "php": 0.64613,
        "pkr": 2.49,
        "pln": 0.01629073,
        "rub": 0.524466,
        "sar": 0.02130347,
        "sek": 0.03536276,
        "sgd": 0.00218922,
        "sol": -0.000061985269102236,
        "thb": 0.181957,
        "try": 0.280691,
        "twd": 0.129111,
        "uah": 0.390941,
        "usd": 0.00574282,
        "vef": 0.00057503,
        "vnd": 150.34,
        "xag": 0.00002237,
        "xau": 0.00000143,
        "xdr": 0.00642327,
        "xlm": -0.00043588229729874,
        "xrp": -0.006140164038487272,
        "yfi": -0.000004833158038818,
        "zar": 0.075558,
        "bits": -0.06387595435646354,
        "link": -0.001218682658747125,
        "sats": -6.38759543564629
      },
      "price_change_percentage_1h_in_currency": {},
      "price_change_percentage_24h_in_currency": {
        "aed": 0.58487,
        "ars": 0.69333,
        "aud": 0.77224,
        "bch": 6.89569,
        "bdt": 0.91265,
        "bhd": 0.67915,
        "bmd": 0.58487,
        "bnb": 0.06825,
        "brl": 0.39537,
        "btc": -0.43445,
        "cad": 0.51055,
        "chf": 0.56496,
        "clp": 0.58487,
        "cny": 0.52666,
        "czk": 0.50132,
        "dkk": 0.49684,
        "dot": 0.44727,
        "eos": 1.50715,
        "eth": -1.57268,
        "eur": 0.79851,
        "gbp": 0.52135,
        "gel": 0.21094,
        "hkd": 0.67612,
        "huf": 0.70431,
        "idr": 0.53387,
        "ils": 0.58102,
        "inr": -0.48392,
        "jpy": 0.22575,
        "krw": 0.89602,
        "kwd": 0.6918,
        "lkr": 0.91224,
        "ltc": 0.70766,
        "mmk": 0.58487,
        "mxn": 0.32872,
        "myr": 0.78536,
        "ngn": 0.88823,
        "nok": 0.50083,
        "nzd": 0.70908,
        "php": 1.08944,
        "pkr": 0.91097,
        "pln": 0.44566,
        "rub": 0.65602,
        "sar": 0.57814,
        "sek": 0.38015,
        "sgd": 0.17247,
        "sol": -0.52174,
        "thb": 0.56487,
        "try": 0.64326,
        "twd": 0.41034,
        "uah": 0.91131,
        "usd": 0.58487,
        "vef": 0.58487,
        "vnd": 0.58136,
        "xag": 0.15891,
        "xau": 0.65267,
        "xdr": 0.9258,
        "xlm": -0.00747,
        "xrp": -0.83518,
        "yfi": -1.19041,
        "zar": 0.44948,
        "bits": -0.43445,
        "link": -1.05847,
        "sats": -0.43445
      },
      "price_change_percentage_7d_in_currency": {
        "aed": 0.36909,
        "ars": -0.17159,
        "aud": 2.73987,
        "bch": 0.68351,
        "bdt": 0.21551,
        "bhd": 0.22498,
        "bmd": 0.36909,
        "bnb": 5.5713,
        "brl": 0.0239,
        "btc": 5.34289,
        "cad": 1.53922,
        "chf": 1.07311,
        "clp": 1.4977,
        "cny": 0.48109,
        "czk": 0.18605,
        "dkk": -0.09574,
        "dot": 21.70529,
        "eos": 6.63488,
        "eth": 7.21098,
        "eur": -0.09194,
        "gbp": 0.28681,
        "gel": -0.92481,
        "hkd": 0.30941,
        "huf": -0.86489,
        "idr": 0.26516,
        "ils": 1.57662,
        "inr": 0.8731,
        "jpy": 0.37327,
        "krw": 1.20569,
        "kwd": 0.71515,
        "lkr": 1.38364,
        "ltc": 3.08179,
        "mmk": 0.36909,
        "mxn": 1.77483,
        "myr": 2.49728,
        "ngn": 1.73072,
        "nok": 1.85987,
        "nzd": 1.65381,
        "php": 1.42165,
        "pkr": 0.19123,
        "pln": 0.10845,
        "rub": -2.51061,
        "sar": 0.31135,
        "sek": 0.81895,
        "sgd": 0.70545,
        "sol": 7.79836,
        "thb": 0.34869,
        "try": 0.70241,
        "twd": 0.44224,
        "uah": -0.58289,
        "usd": 0.36909,
        "vef": 0.36909,
        "vnd": 0.46159,
        "xag": 6.51521,
        "xau": 7.89895,
        "xdr": 0.09618,
        "xlm": -0.10248,
        "xrp": 8.60938,
        "yfi": 11.98651,
        "zar": 0.97472,
        "bits": 5.34289,
        "link": 6.14158,
        "sats": 5.34289
      },
      "price_change_percentage_14d_in_currency": {
        "aed": 0.36174,
        "ars": -0.40265,
        "aud": 2.39701,
        "bch": 4.26034,
        "bdt": 0.18418,
        "bhd": 0.03347,
        "bmd": 0.36174,
        "bnb": 10.71088,
        "brl": -1.33316,
        "btc": 9.5341,
        "cad": 1.66595,
        "chf": 1.52261,
        "clp": 0.93249,
        "cny": 0.47228,
        "czk": 0.01039,
        "dkk": -0.2279,
        "dot": 16.51014,
        "eos": 13.37121,
        "eth": 9.64889,
        "eur": -0.23367,
        "gbp": 0.25673,
        "gel": -1.47639,
        "hkd": 0.4176,
        "huf": -0.87824,
        "idr": 0.29551,
        "ils": 0.1468,
        "inr": 1.86211,
        "jpy": 0.49643,
        "krw": 1.52889,
        "kwd": 0.06503,
        "lkr": 1.40887,
        "ltc": 5.20135,
        "mmk": 0.36174,
        "mxn": 1.63527,
        "myr": 2.60702,
        "ngn": -0.05117,
        "nok": 0.25433,
        "nzd": 1.59675,
        "php": 1.73514,
        "pkr": 0.14476,
        "pln": 0.01179,
        "rub": 1.32593,
        "sar": 0.35906,
        "sek": 0.61,
        "sgd": 0.85111,
        "sol": 11.96609,
        "thb": 1.48281,
        "try": 0.97609,
        "twd": 0.02715,
        "uah": -0.41403,
        "usd": 0.36174,
        "vef": 0.36174,
        "vnd": 0.53354,
        "xag": 14.96942,
        "xau": 12.17463,
        "xdr": -0.13674,
        "xlm": 0.80504,
        "xrp": 8.72434,
        "yfi": 7.86203,
        "zar": 1.90897,
        "bits": 9.5341,
        "link": 12.35819,
        "sats": 9.5341
      },
      "price_change_percentage_30d_in_currency": {
        "aed": 0.3547,
        "ars": -0.34974,
        "aud": 4.01398,
        "bch": 2.19148,
        "bdt": 0.82483,
        "bhd": 0.35053,
        "bmd": 0.36836,
        "bnb": -0.67652,
        "brl": 2.74647,
        "btc": -2.46555,
        "cad": 2.25741,
        "chf": 4.32095,
        "clp": 6.42885,
        "cny": 1.09571,
        "czk": 4.26287,
        "dkk": 3.02747,
        "dot": 29.49059,
        "eos": 8.45761,
        "eth": -5.75256,
        "eur": 3.02015,
        "gbp": 1.9772,
        "gel": 0.74428,
        "hkd": 0.50261,
        "huf": 6.5324,
        "idr": 1.50922,
        "ils": 0.43751,
        "inr": 3.44268,
        "jpy": 2.74076,
        "krw": 5.37929,
        "kwd": 0.8222,
        "lkr": 2.28372,
        "ltc": 0.42762,
        "mmk": 0.36406,
        "mxn": 5.39817,
        "myr": 3.72662,
        "ngn": 1.75237,
        "nok": 2.854,
        "nzd": 4.95223,
        "php": 5.53704,
        "pkr": 0.2646,
        "pln": 4.49402,
        "rub": 5.79558,
        "sar": 0.41121,
        "sek": 5.2152,
        "sgd": 2.20413,
        "sol": -1.84192,
        "thb": 6.01564,
        "try": 1.57368,
        "twd": 2.39265,
        "uah": 2.08506,
        "usd": 0.36836,
        "vef": 0.36836,
        "vnd": 1.49202,
        "xag": 10.05137,
        "xau": 17.49568,
        "xdr": 2.91247,
        "xlm": -6.54921,
        "xrp": 0.29181,
        "yfi": 8.90578,
        "zar": 7.8906,
        "bits": -2.46555,
        "link": 0.6635,
        "sats": -2.46555
      },
      "price_change_percentage_60d_in_currency": {
        "aed": 0.52545,
        "ars": -2.70561,
        "aud": 0.87367,
        "bch": 31.10512,
        "bdt": 0.84396,
        "bhd": 0.61006,
        "bmd": 0.52545,
        "bnb": 44.2813,
        "brl": -0.30602,
        "btc": 32.79177,
        "cad": 1.73193,
        "chf": 2.89323,
        "clp": 7.04099,
        "cny": -0.27433,
        "czk": 4.3029,
        "dkk": 3.28007,
        "dot": 52.21295,
        "eos": 56.00033,
        "eth": 44.80324,
        "eur": 3.23045,
        "gbp": 3.32434,
        "gel": 0.15175,
        "hkd": 0.98569,
        "huf": 5.27607,
        "idr": 1.75217,
        "ils": 0.61187,
        "inr": 2.99416,
        "jpy": 3.12083,
        "krw": 5.13743,
        "kwd": 1.04328,
        "lkr": 2.246,
        "ltc": 26.68787,
        "mmk": 0.52114,
        "mxn": 4.65257,
        "myr": 0.927,
        "ngn": -2.22491,
        "nok": 0.15561,
        "nzd": 4.2314,
        "php": 3.4875,
        "pkr": 0.30316,
        "pln": 5.11156,
        "rub": 8.57795,
        "sar": 0.62099,
        "sek": 6.18951,
        "sgd": 1.68654,
        "sol": 52.96278,
        "thb": 5.704,
        "try": 3.06489,
        "twd": 2.45679,
        "uah": 2.20166,
        "usd": 0.52545,
        "vef": 0.52545,
        "vnd": 0.88286,
        "xag": 48.21408,
        "xau": 11.6682,
        "xdr": 2.64364,
        "xlm": 25.4945,
        "xrp": 41.93999,
        "yfi": 36.51448,
        "zar": 6.63799,
        "bits": 32.79177,
        "link": 41.37661,
        "sats": 32.79177
      },
      "price_change_percentage_200d_in_currency": {
        "aed": -0.3419,
        "ars": -2.93251,
        "aud": -4.07635,
        "bch": 27.97367,
        "bdt": 0.39449,
        "bhd": -0.37018,
        "bmd": -0.3419,
        "bnb": 44.49712,
        "brl": -3.27405,
        "btc": 68.93646,
        "cad": -0.19999,
        "chf": -0.4297,
        "clp": -4.06801,
        "cny": -3.32558,
        "czk": 1.69544,
        "dkk": 1.27684,
        "dot": 231.89184,
        "eos": 533.47482,
        "eth": 114.26605,
        "eur": 1.17859,
        "gbp": 1.54222,
        "gel": -0.71237,
        "hkd": 0.21398,
        "huf": 0.32616,
        "idr": 2.77133,
        "ils": -5.88504,
        "inr": 6.09776,
        "jpy": 7.94264,
        "krw": 8.43869,
        "kwd": 0.43244,
        "lkr": 3.88653,
        "ltc": 114.62348,
        "mmk": -0.32718,
        "mxn": -3.13405,
        "myr": -5.05211,
        "ngn": -8.69381,
        "nok": -2.33634,
        "nzd": 3.11786,
        "php": 5.86015,
        "pkr": -2.07438,
        "pln": 1.65531,
        "rub": -3.90871,
        "sar": -0.31934,
        "sek": 0.74365,
        "sgd": -0.02662,
        "sol": 167.55955,
        "thb": 2.88698,
        "try": 7.34717,
        "twd": 5.03412,
        "uah": 5.81203,
        "usd": -0.3419,
        "vef": -0.3419,
        "vnd": -0.59124,
        "xag": -41.53154,
        "xau": -19.38731,
        "xdr": 1.27655,
        "xlm": 129.37809,
        "xrp": 121.27796,
        "yfi": 122.77362,
        "zar": -2.60034,
        "bits": 68.93646,
        "link": 173.53834,
        "sats": 68.93646
      },
      "price_change_percentage_1y_in_currency": {
        "aed": -1.30862,
        "ars": 29.17096,
        "aud": -9.48488,
        "bch": -33.48827,
        "bdt": -0.34485,
        "bhd": -0.76072,
        "bmd": -1.29384,
        "bnb": -2.12272,
        "brl": -10.10493,
        "btc": 21.81046,
        "cad": -4.66562,
        "chf": -10.5287,
        "clp": -2.90186,
        "cny": -6.1275,
        "czk": -8.75251,
        "dkk": -7.07775,
        "dot": 219.90825,
        "eos": 677.02464,
        "eth": -11.11883,
        "eur": -6.8083,
        "gbp": -3.74657,
        "gel": -4.67296,
        "hkd": -0.66868,
        "huf": -10.148,
        "idr": 1.00567,
        "ils": -16.1764,
        "inr": 8.28773,
        "jpy": 5.20761,
        "krw": 1.54336,
        "kwd": -1.39951,
        "lkr": 4.97303,
        "ltc": 57.9907,
        "mmk": -1.20868,
        "mxn": -12.45773,
        "myr": -10.46648,
        "ngn": -10.92866,
        "nok": -8.39888,
        "nzd": -1.68785,
        "php": 4.44414,
        "pkr": -1.69573,
        "pln": -4.93064,
        "rub": -4.83676,
        "sar": -1.22503,
        "sek": -6.79848,
        "sgd": -5.17083,
        "sol": 47.99526,
        "thb": -4.09164,
        "try": 15.50674,
        "twd": -4.88909,
        "uah": 4.31172,
        "usd": -1.29384,
        "vef": -1.29384,
        "vnd": 1.64359,
        "xag": -51.96645,
        "xau": -32.22986,
        "xdr": -7.40885,
        "xlm": 58.49099,
        "xrp": 59.16434,
        "yfi": 94.35008,
        "zar": -7.73232,
        "bits": 21.81046,
        "link": 56.64652,
        "sats": 21.81046
      },
      "market_cap_change_24h_in_currency": {
        "aed": -94975.44861376286,
        "ars": 289818497,
        "aud": 552263,
        "bch": 28373,
        "bdt": 83708175,
        "bhd": 67205,
        "bmd": -25861.252175211906,
        "bnb": -2468.718008866883,
        "brl": -2293817.672884226,
        "btc": -32.98515788590339,
        "cad": -259805.0544050932,
        "chf": -55090.28479671478,
        "clp": -23945603.867858887,
        "cny": -1050635.9617197514,
        "czk": -4409178.840659142,
        "dkk": -1406422.8081738949,
        "dot": -1012872.4751012027,
        "eos": 11655407,
        "eth": -2238.396741274002,
        "eur": 378664,
        "gbp": -123247.3019914329,
        "gel": -2249280.7003754377,
        "hkd": 1345203,
        "huf": 78751661,
        "idr": -2316914998.8344727,
        "ils": -107303.22842216492,
        "inr": -222135631.55152512,
        "jpy": -128882985.87060547,
        "krw": 977814894,
        "kwd": 63322,
        "lkr": 214623218,
        "ltc": 1380,
        "mmk": -54303715.930114746,
        "mxn": -10528039.994336128,
        "myr": 1639977,
        "ngn": 870277844,
        "nok": -2026512.3596718311,
        "nzd": 423417,
        "php": 64482838,
        "pkr": 189390718,
        "pln": -1219263.5943139791,
        "rub": 10449542,
        "sar": -151761.65965521336,
        "sek": -4447707.401230574,
        "sgd": -1188679.224659741,
        "sol": -24923.89994174475,
        "thb": -2270009.9154405594,
        "try": 4474170,
        "twd": -12948135.742652893,
        "uah": 29776735,
        "usd": -25861.252175211906,
        "vef": -2589.487180303782,
        "vnd": -881324838.1630859,
        "xag": -13601.551773527171,
        "xau": 26.94,
        "xdr": 503768,
        "xlm": -4300491.144906998,
        "xrp": -2346675.518454641,
        "yfi": -1735.3571801549842,
        "zar": -5465677.680809498,
        "bits": -32985157.88590336,
        "link": -454791.1608431488,
        "sats": -3298515788.590332
      },
      "market_cap_change_percentage_24h_in_currency": {
        "aed": -0.01186,
        "ars": 0.09596,
        "aud": 0.1744,
        "bch": 6.29271,
        "bdt": 0.31397,
        "bhd": 0.08186,
        "bmd": -0.01186,
        "bnb": -0.6942,
        "brl": -0.20023,
        "btc": -1.01065,
        "cad": -0.08574,
        "chf": -0.03165,
        "clp": -0.01186,
        "cny": -0.06973,
        "czk": -0.09492,
        "dkk": -0.09937,
        "dot": -0.58853,
        "eos": 0.39703,
        "eth": -2.05982,
        "eur": 0.20051,
        "gbp": -0.07501,
        "gel": -0.38357,
        "hkd": 0.07885,
        "huf": 0.10687,
        "idr": -0.06255,
        "ils": -0.01569,
        "inr": -1.07431,
        "jpy": -0.36885,
        "krw": 0.29744,
        "kwd": 0.09444,
        "lkr": 0.31357,
        "ltc": 0.03428,
        "mmk": -0.01186,
        "mxn": -0.26649,
        "myr": 0.18744,
        "ngn": 0.2897,
        "nok": -0.0954,
        "nzd": 0.11161,
        "php": 0.48972,
        "pkr": 0.3123,
        "pln": -0.15024,
        "rub": 0.05887,
        "sar": -0.01855,
        "sek": -0.21536,
        "sgd": -0.42181,
        "sol": -0.94652,
        "thb": -0.03174,
        "try": 0.04618,
        "twd": -0.18535,
        "uah": 0.31264,
        "usd": -0.01186,
        "vef": -0.01186,
        "vnd": -0.01535,
        "xag": -0.43529,
        "xau": 0.05554,
        "xdr": 0.32705,
        "xlm": -0.33276,
        "xrp": -1.4375,
        "yfi": -1.92233,
        "zar": -0.14645,
        "bits": -1.01065,
        "link": -1.7768,
        "sats": -1.01065
      },
      "total_supply": 220697826.4917949,
      "max_supply": null,
      "max_supply_infinite": true,
      "circulating_supply": 220697826.4917949,
      "outstanding_supply": null,
      "last_updated": "2026-03-30T04:33:10.006Z"
    },
    "community_data": {
      "facebook_likes": null,
      "reddit_average_posts_48h": 0,
      "reddit_average_comments_48h": 0,
      "reddit_subscribers": 0,
      "reddit_accounts_active_48h": 0,
      "telegram_channel_user_count": 175223
    },
    "developer_data": {
      "forks": 0,
      "stars": 0,
      "subscribers": 0,
      "total_issues": 0,
      "closed_issues": 0,
      "pull_requests_merged": 0,
      "pull_request_contributors": 0,
      "code_additions_deletions_4_weeks": {
        "additions": null,
        "deletions": null
      },
      "commit_count_4_weeks": 0,
      "last_4_weeks_commit_activity_series": []
    },
    "status_updates": [],
    "last_updated": "2026-03-30T04:33:10.006Z",
    "tickers": [
      {
        "base": "0X8A60E489004CA22D775C5F2C657598278D17D9C2",
        "target": "0XDAC17F958D2EE523A2206206994597C13D831EC7",
        "market": {
          "name": "Uniswap V3 (Ethereum)",
          "identifier": "uniswap_v3",
          "has_trading_incentive": false
        },
        "last": 0.9840311625,
        "volume": 2.0589001095,
        "converted_last": {
          "btc": 0.00001452,
          "eth": 0.00047827,
          "usd": 0.979845
        },
        "converted_volume": {
          "btc": 0.00002991,
          "eth": 0.00098519,
          "usd": 2.02
        },
        "trust_score": null,
        "bid_ask_spread_percentage": 0.60283,
        "timestamp": "2026-03-29T06:20:06+00:00",
        "last_traded_at": "2026-03-29T06:20:06+00:00",
        "last_fetch_at": "2026-03-30T05:55:23+00:00",
        "is_anomaly": false,
        "is_stale": true,
        "trade_url": "https://app.uniswap.org/explore/tokens/ethereum/0x8a60e489004ca22d775c5f2c657598278d17d9c2",
        "token_info_url": null,
        "coin_id": "usda-2",
        "target_coin_id": "tether",
        "coin_mcap_usd": 217971393.20242098
      },
      {
        "base": "0X9356086146BE5158E98AD827E21B5CF944699894",
        "target": "0X55D398326F99059FF775485246999027B3197955",
        "market": {
          "name": "PancakeSwap V3 (BSC)",
          "identifier": "pancakeswap-v3-bsc",
          "has_trading_incentive": false
        },
        "last": 0.9885663114,
        "volume": 2.0638384118,
        "converted_last": {
          "btc": 0.00001464,
          "eth": 0.00048232,
          "usd": 0.987681
        },
        "converted_volume": {
          "btc": 0.00003022,
          "eth": 0.00099593,
          "usd": 2.04
        },
        "trust_score": null,
        "bid_ask_spread_percentage": 0.603299,
        "timestamp": "2026-03-29T20:33:10+00:00",
        "last_traded_at": "2026-03-29T20:33:10+00:00",
        "last_fetch_at": "2026-03-30T05:56:21+00:00",
        "is_anomaly": false,
        "is_stale": true,
        "trade_url": "https://pancakeswap.finance/swap?inputCurrency=0x9356086146be5158e98ad827e21b5cf944699894&outputCurrency=0x55d398326f99059ff775485246999027b3197955",
        "token_info_url": null,
        "coin_id": "usda-2",
        "target_coin_id": "binance-bridged-usdt-bnb-smart-chain",
        "coin_mcap_usd": 217971393.20242098
      }
    ]
  },
  "chart": {
    "prices": [
      [
        1772884847975,
        0.9839874589333524
      ],
      [
        1772888449943,
        0.9840222653827969
      ],
      [
        1772892044931,
        0.9840331401355106
      ],
      [
        1772895647500,
        0.98401806930007
      ],
      [
        1772899245483,
        0.9840224412652706
      ],
      [
        1772902843815,
        0.9840292199439894
      ],
      [
        1772906443823,
        0.9840132880232328
      ],
      [
        1772910047483,
        0.9840323416621292
      ],
      [
        1772913635432,
        0.9839835422050269
      ],
      [
        1772917247194,
        0.984042227021648
      ],
      [
        1773226851115,
        0.9840019040119615
      ],
      [
        1773230456241,
        0.9839375762006324
      ],
      [
        1773234053336,
        0.9840603544520995
      ],
      [
        1773237654198,
        0.9840735153680269
      ],
      [
        1773241250579,
        0.984063897046103
      ],
      [
        1773244853167,
        0.9841572887116226
      ],
      [
        1773248454585,
        0.9841247243113738
      ],
      [
        1773252052565,
        0.9842155178807742
      ],
      [
        1773255651962,
        0.9841740462456158
      ],
      [
        1773608574196,
        0.9841617509950065
      ],
      [
        1773612177417,
        0.9841585355378235
      ],
      [
        1773615795493,
        0.9841581193406203
      ],
      [
        1773619407954,
        0.9842008207306744
      ],
      [
        1773623002419,
        0.9841294301537274
      ],
      [
        1773626593526,
        0.9841485899668045
      ],
      [
        1773630170983,
        0.9841350223826417
      ],
      [
        1773633809973,
        0.9840864993219439
      ],
      [
        1773637389447,
        0.9840631624000711
      ],
      [
        1773723733345,
        0.98406411953278
      ],
      [
        1773727361836,
        0.9840290380372771
      ],
      [
        1773730949778,
        0.9840270264974397
      ],
      [
        1773734477582,
        0.9840510604479727
      ],
      [
        1773738074439,
        0.9840339772316773
      ],
      [
        1773741663307,
        0.984124243117406
      ],
      [
        1773745280304,
        0.984079213915192
      ],
      [
        1773749026205,
        0.9840534719999083
      ],
      [
        1773752622132,
        0.9840734848522095
      ],
      [
        1773763440878,
        0.9841427629775381
      ],
      [
        1773767031689,
        0.9841663570339917
      ],
      [
        1773770616604,
        0.9842053189373999
      ],
      [
        1773774190503,
        0.9841563189128885
      ],
      [
        1773777812294,
        0.9841842630873457
      ],
      [
        1773781434104,
        0.9842000482244004
      ],
      [
        1773784986250,
        0.9841501171637663
      ],
      [
        1773788603538,
        0.984182816261
      ],
      [
        1773792248618,
        0.9842344843982866
      ],
      [
        1773810194040,
        0.9842513501231481
      ],
      [
        1773813755494,
        0.9842751629061237
      ],
      [
        1773817415039,
        0.9841640532727864
      ],
      [
        1773820973480,
        0.9841352076947977
      ],
      [
        1773824573243,
        0.9841326390219679
      ],
      [
        1773828171810,
        0.9841878148297775
      ],
      [
        1773831769522,
        0.9841651754454089
      ],
      [
        1773835381234,
        0.9841898691198054
      ],
      [
        1773838965449,
        0.9841606081297968
      ],
      [
        1773871340730,
        0.9840775364762506
      ],
      [
        1773874930741,
        0.9840873421477916
      ],
      [
        1773878524851,
        0.9840483367085168
      ],
      [
        1773882132177,
        0.9840888955463193
      ],
      [
        1773885727338,
        0.9840945185591273
      ],
      [
        1773889322471,
        0.9840814369987435
      ],
      [
        1773892912246,
        0.9840891303848239
      ],
      [
        1773896535773,
        0.984046026520498
      ],
      [
        1773900114469,
        0.9840158290780718
      ],
      [
        1773903718815,
        0.9840144360931785
      ],
      [
        1774270980714,
        0.9836648181650547
      ],
      [
        1774274580922,
        0.9837958563751364
      ],
      [
        1774278157962,
        0.9838717271046739
      ],
      [
        1774281754687,
        0.9837967999917105
      ],
      [
        1774285402354,
        0.9838090303675902
      ],
      [
        1774289005673,
        0.9837291414648301
      ],
      [
        1774292601584,
        0.9837181177262858
      ],
      [
        1774296199690,
        0.9837435660925203
      ],
      [
        1774299805669,
        0.9838090028002942
      ],
      [
        1774303398391,
        0.9838842077533593
      ],
      [
        1774307000356,
        0.983730497092469
      ],
      [
        1774310606679,
        0.9837468808534598
      ],
      [
        1774339301793,
        0.9848474207613213
      ],
      [
        1774342901408,
        0.9847461939703358
      ],
      [
        1774346501031,
        0.9847327574259951
      ],
      [
        1774350106942,
        0.9846917096776536
      ],
      [
        1774353694942,
        0.9847048676827301
      ],
      [
        1774357292144,
        0.9848373891178263
      ],
      [
        1774360878102,
        0.9849032018245627
      ],
      [
        1774364483296,
        0.9846744746453524
      ],
      [
        1774368078822,
        0.9847935046092169
      ],
      [
        1774371688418,
        0.9847045953873709
      ],
      [
        1774375287880,
        0.9846428267013403
      ],
      [
        1774378893309,
        0.9845722657466107
      ],
      [
        1774382484977,
        0.9846217615905236
      ],
      [
        1774386095431,
        0.9845211188069475
      ],
      [
        1774389690933,
        0.9844521596847875
      ],
      [
        1774393277988,
        0.9845221106822033
      ],
      [
        1774396874944,
        0.9845699000150798
      ],
      [
        1774400475881,
        0.9846133305395285
      ],
      [
        1774422077830,
        0.9847054080786866
      ],
      [
        1774425679267,
        0.9846741052415735
      ],
      [
        1774429288309,
        0.9846623245598907
      ],
      [
        1774432882662,
        0.9846623245598907
      ],
      [
        1774436411054,
        0.9846623245598907
      ],
      [
        1774440001942,
        0.9846623245598907
      ],
      [
        1774443616623,
        0.9846623245598907
      ],
      [
        1774447214291,
        0.9846623245598907
      ],
      [
        1774450818671,
        0.9846623245598907
      ],
      [
        1774587739636,
        0.9833882902818919
      ],
      [
        1774591347021,
        0.9833706525310488
      ],
      [
        1774594948678,
        0.983407537301813
      ],
      [
        1774598539534,
        0.9833099730615413
      ],
      [
        1774602150150,
        0.9833987659076834
      ],
      [
        1774605732455,
        0.9833941370877831
      ],
      [
        1774609331177,
        0.9834630651871602
      ],
      [
        1774612949977,
        0.9834883839394254
      ],
      [
        1774616530290,
        0.9835004843221817
      ],
      [
        1774663326317,
        0.9835004843221817
      ],
      [
        1774666941582,
        0.9835004843221817
      ],
      [
        1774670533476,
        0.9835004843221817
      ],
      [
        1774674135510,
        0.9835004843221817
      ],
      [
        1774677742628,
        0.9835004843221817
      ],
      [
        1774681336553,
        0.9835004843221817
      ],
      [
        1774684946051,
        0.9835004843221817
      ],
      [
        1774688538961,
        0.9835004843221817
      ],
      [
        1774692131902,
        0.9835004843221817
      ],
      [
        1774706508865,
        0.9878949733490245
      ],
      [
        1774710115521,
        0.9878650747036968
      ],
      [
        1774713714116,
        0.9878370541195132
      ],
      [
        1774717313334,
        0.9878574850204378
      ],
      [
        1774720901045,
        0.987861818242699
      ],
      [
        1774724510167,
        0.9878441936835289
      ],
      [
        1774728119522,
        0.9878681144342673
      ],
      [
        1774731750884,
        0.9877539921625513
      ],
      [
        1774735345803,
        0.9877443714627921
      ],
      [
        1774738958900,
        0.9877325692417235
      ],
      [
        1774742554551,
        0.98777544206392
      ],
      [
        1774746147432,
        0.9878612268476169
      ],
      [
        1774749784718,
        0.9877483174671319
      ],
      [
        1774753447543,
        0.987746604395893
      ],
      [
        1774756989110,
        0.987752221908556
      ],
      [
        1774760654845,
        0.9877634855816061
      ],
      [
        1774767778608,
        0.9832311604012635
      ],
      [
        1774771422122,
        0.9832096193417893
      ],
      [
        1774774977959,
        0.9832440416851277
      ],
      [
        1774778570989,
        0.9832243469746643
      ],
      [
        1774782164239,
        0.9832527362533479
      ],
      [
        1774785754993,
        0.9832605936263875
      ],
      [
        1774789387115,
        0.9832430796450037
      ],
      [
        1774792978932,
        0.9850333721555601
      ],
      [
        1774796584632,
        0.9876924412420457
      ],
      [
        1774800172681,
        0.9876970264344009
      ],
      [
        1774803765392,
        0.9876813414885245
      ],
      [
        1774807368997,
        0.9877125561623826
      ],
      [
        1774810953319,
        0.9876970106228671
      ],
      [
        1774814555055,
        0.987729904151245
      ],
      [
        1774818158483,
        0.9877271998136467
      ],
      [
        1774821770725,
        0.9877542316065117
      ],
      [
        1774825375954,
        0.9877509088249704
      ],
      [
        1774828959644,
        0.987761785761477
      ],
      [
        1774832573147,
        0.9877296951583713
      ],
      [
        1774836194812,
        0.9876411343721233
      ],
      [
        1774839735807,
        0.9876690686571217
      ],
      [
        1774843341411,
        0.9876073878676922
      ],
      [
        1774845190000,
        0.9876463065689717
      ],
      [
        1774846923561,
        0.9876463065689717
      ]
    ],
    "market_caps": [
      [
        1772884847975,
        217164135.42400888
      ],
      [
        1772888449943,
        217171817.14015535
      ],
      [
        1772892044931,
        217175479.71447638
      ],
      [
        1772895647500,
        217171378.3889859
      ],
      [
        1772899245483,
        217171856.46454084
      ],
      [
        1772902843815,
        217173353.3259462
      ],
      [
        1772906443823,
        217167595.92928612
      ],
      [
        1772910047483,
        217175880.7751024
      ],
      [
        1772913635432,
        217163271.00946543
      ],
      [
        1772917247194,
        217176222.63537115
      ],
      [
        1773226851115,
        217169272.0104405
      ],
      [
        1773230456241,
        217153126.40090096
      ],
      [
        1773234053336,
        217176355.9660192
      ],
      [
        1773237654198,
        217188914.8073
      ],
      [
        1773241250579,
        217181005.1681942
      ],
      [
        1773244853167,
        217207290.05200705
      ],
      [
        1773248454585,
        217204535.39852872
      ],
      [
        1773252052565,
        217216048.66473785
      ],
      [
        1773255651962,
        217205314.88400227
      ],
      [
        1773608574196,
        216435331.7290141
      ],
      [
        1773612177417,
        217201902.3686176
      ],
      [
        1773615795493,
        217202458.4020123
      ],
      [
        1773619407954,
        217210587.1812582
      ],
      [
        1773623002419,
        217195478.8661365
      ],
      [
        1773626593526,
        217197541.87987518
      ],
      [
        1773630170983,
        217198514.6106438
      ],
      [
        1773633809973,
        217191845.31893337
      ],
      [
        1773637389447,
        217180853.69992587
      ],
      [
        1773723733345,
        217180666.0715782
      ],
      [
        1773727361836,
        217171714.03789273
      ],
      [
        1773730949778,
        217173809.9274116
      ],
      [
        1773734477582,
        217175974.95151314
      ],
      [
        1773738074439,
        217174412.5921637
      ],
      [
        1773741663307,
        217191265.97981355
      ],
      [
        1773745280304,
        217184396.23854566
      ],
      [
        1773749026205,
        217176976.653402
      ],
      [
        1773752622132,
        217183131.84532684
      ],
      [
        1773763440878,
        217198421.3947953
      ],
      [
        1773767031689,
        217203248.39446658
      ],
      [
        1773770616604,
        217212551.6663761
      ],
      [
        1773774190503,
        217204652.23501372
      ],
      [
        1773777812294,
        217207580.38948286
      ],
      [
        1773781434104,
        217211064.13897404
      ],
      [
        1773784986250,
        217200044.44959942
      ],
      [
        1773788603538,
        217207229.5412213
      ],
      [
        1773792248618,
        217218664.13654384
      ],
      [
        1773810194040,
        217227062.62486786
      ],
      [
        1773813755494,
        217231324.56660303
      ],
      [
        1773817415039,
        217209456.35656625
      ],
      [
        1773820973480,
        217202651.99280557
      ],
      [
        1773824573243,
        217204907.84150684
      ],
      [
        1773828171810,
        217211175.93273723
      ],
      [
        1773831769522,
        217211160.06603172
      ],
      [
        1773835381234,
        217217191.35676432
      ],
      [
        1773838965449,
        217207359.93731982
      ],
      [
        1773871340730,
        217184026.0309866
      ],
      [
        1773874930741,
        217184259.81473857
      ],
      [
        1773878524851,
        217177581.69821754
      ],
      [
        1773882132177,
        217186532.95597783
      ],
      [
        1773885727338,
        217187773.9441264
      ],
      [
        1773889322471,
        217188201.04653475
      ],
      [
        1773892912246,
        217188104.95158967
      ],
      [
        1773896535773,
        217177660.6020259
      ],
      [
        1773900114469,
        217171552.07227063
      ],
      [
        1773903718815,
        217170407.3264886
      ],
      [
        1774270980714,
        217092949.79521453
      ],
      [
        1774274580922,
        217122419.89673626
      ],
      [
        1774278157962,
        217137041.2458903
      ],
      [
        1774281754687,
        217120885.63006604
      ],
      [
        1774285402354,
        217113957.3235208
      ],
      [
        1774289005673,
        217106824.59915337
      ],
      [
        1774292601584,
        217104716.597528
      ],
      [
        1774296199690,
        217110333.06924766
      ],
      [
        1774299805669,
        217122265.52301866
      ],
      [
        1774303398391,
        217141372.35844338
      ],
      [
        1774307000356,
        217100814.7007784
      ],
      [
        1774310606679,
        217108968.60743356
      ],
      [
        1774339301793,
        217349689.74973568
      ],
      [
        1774342901408,
        217331344.74402577
      ],
      [
        1774346501031,
        217326217.07236236
      ],
      [
        1774350106942,
        217322353.58155027
      ],
      [
        1774353694942,
        217322542.3009905
      ],
      [
        1774357292144,
        217351477.2130028
      ],
      [
        1774360878102,
        217365996.0459809
      ],
      [
        1774364483296,
        217327348.67875645
      ],
      [
        1774368078822,
        217340928.48284698
      ],
      [
        1774371688418,
        217322164.03694555
      ],
      [
        1774375287880,
        217308531.81979442
      ],
      [
        1774378893309,
        217294895.81753665
      ],
      [
        1774382484977,
        217303882.798013
      ],
      [
        1774386095431,
        217282064.6928389
      ],
      [
        1774389690933,
        217266474.15774012
      ],
      [
        1774393277988,
        217281912.18983886
      ],
      [
        1774396874944,
        217294283.3722911
      ],
      [
        1774400475881,
        217292437.05824146
      ],
      [
        1774422077830,
        217317084.83957255
      ],
      [
        1774425679267,
        217315434.9280356
      ],
      [
        1774429288309,
        217312834.95719242
      ],
      [
        1774432882662,
        217312834.95719242
      ],
      [
        1774436411054,
        217312834.95719242
      ],
      [
        1774440001942,
        217312834.95719242
      ],
      [
        1774443616623,
        217312834.95719242
      ],
      [
        1774447214291,
        217312834.95719242
      ],
      [
        1774450818671,
        217312834.95719242
      ],
      [
        1774587739636,
        217033921.2850009
      ],
      [
        1774591347021,
        217027765.7477576
      ],
      [
        1774594948678,
        217035962.18472803
      ],
      [
        1774598539534,
        217014373.92071855
      ],
      [
        1774602150150,
        217037935.5342531
      ],
      [
        1774605732455,
        217032948.73838735
      ],
      [
        1774609331177,
        217051033.9718318
      ],
      [
        1774612949977,
        217048666.0985708
      ],
      [
        1774616530290,
        217056419.34188315
      ],
      [
        1774663326317,
        217056419.34188315
      ],
      [
        1774666941582,
        217056419.34188315
      ],
      [
        1774670533476,
        217056419.34188315
      ],
      [
        1774674135510,
        217056419.34188315
      ],
      [
        1774677742628,
        217056419.34188315
      ],
      [
        1774681336553,
        217056419.34188315
      ],
      [
        1774684946051,
        217056419.34188315
      ],
      [
        1774688538961,
        217056419.34188315
      ],
      [
        1774692131902,
        217056419.34188315
      ],
      [
        1774706508865,
        218026094.3993
      ],
      [
        1774710115521,
        218019671.55075434
      ],
      [
        1774713714116,
        218021907.80221626
      ],
      [
        1774717313334,
        218015822.32539216
      ],
      [
        1774720901045,
        218019032.54932892
      ],
      [
        1774724510167,
        218020983.23686865
      ],
      [
        1774728119522,
        218020345.81497732
      ],
      [
        1774731750884,
        217998960.47139096
      ],
      [
        1774735345803,
        217989105.71071061
      ],
      [
        1774738958900,
        217996131.71182653
      ],
      [
        1774742554551,
        218000047.7978982
      ],
      [
        1774746147432,
        218013984.31563938
      ],
      [
        1774749784718,
        217994754.37678888
      ],
      [
        1774753447543,
        217991790.15462616
      ],
      [
        1774756989110,
        217994768.37290126
      ],
      [
        1774760654845,
        217997254.4545962
      ],
      [
        1774767778608,
        216997859.40059274
      ],
      [
        1774771422122,
        217002866.37729377
      ],
      [
        1774774977959,
        216992432.0184689
      ],
      [
        1774778570989,
        216995643.06236818
      ],
      [
        1774782164239,
        216996989.9670605
      ],
      [
        1774785754993,
        217003924.90908718
      ],
      [
        1774789387115,
        217001774.44255015
      ],
      [
        1774792978932,
        217393396.11485046
      ],
      [
        1774796584632,
        217988378.15216294
      ],
      [
        1774800172681,
        217981206.36322224
      ],
      [
        1774803765392,
        217979125.33301762
      ],
      [
        1774807368997,
        217986014.34369275
      ],
      [
        1774810953319,
        217985390.46277723
      ],
      [
        1774814555055,
        217989843.0071287
      ],
      [
        1774818158483,
        217993643.84396508
      ],
      [
        1774821770725,
        217997808.7945428
      ],
      [
        1774825375954,
        217998656.12384868
      ],
      [
        1774828959644,
        217996879.20921195
      ],
      [
        1774832573147,
        217990384.5381734
      ],
      [
        1774836194812,
        217976095.84862828
      ],
      [
        1774839735807,
        217976416.7458021
      ],
      [
        1774843341411,
        217962592.61860386
      ],
      [
        1774845190000,
        217971393.20242098
      ],
      [
        1774846923561,
        217971393.20242098
      ]
    ],
    "total_volumes": [
      [
        1772884847975,
        2.689939504042961
      ],
      [
        1772888449943,
        2.8594489710973185
      ],
      [
        1772892044931,
        2.8594805718055056
      ],
      [
        1772895647500,
        2.859436777791478
      ],
      [
        1772899245483,
        2.859449482190387
      ],
      [
        1772902843815,
        2.8594691802059393
      ],
      [
        1772906443823,
        2.8594228839827567
      ],
      [
        1772910047483,
        2.859478251539015
      ],
      [
        1772913635432,
        2.859336446254409
      ],
      [
        1772917247194,
        2.8595069771909634
      ],
      [
        1773226851115,
        1.544948974626309
      ],
      [
        1773230456241,
        1.5448479756488194
      ],
      [
        1773234053336,
        1.5450407457369026
      ],
      [
        1773237654198,
        1.545061409257455
      ],
      [
        1773241250579,
        1.545046307847048
      ],
      [
        1773244853167,
        1.5451929390245842
      ],
      [
        1773248454585,
        1.5451418107324857
      ],
      [
        1773252052565,
        1.5452843627248916
      ],
      [
        1773255651962,
        1.5452192494766823
      ],
      [
        1773608574196,
        101.37616090563147
      ],
      [
        1773612177417,
        101.37582968903578
      ],
      [
        1773615795493,
        101.3757868175519
      ],
      [
        1773619407954,
        101.38018538616589
      ],
      [
        1773623002419,
        101.37283161265417
      ],
      [
        1773626593526,
        101.37480521942305
      ],
      [
        1773630170983,
        101.37340765485219
      ],
      [
        1773633809973,
        101.36840940979343
      ],
      [
        1773637389447,
        101.36600552898375
      ],
      [
        1773723733345,
        12.778750617135673
      ],
      [
        1773727361836,
        12.778295059745247
      ],
      [
        1773730949778,
        12.778268938514497
      ],
      [
        1773734477582,
        12.778581035921679
      ],
      [
        1773738074439,
        12.778359198587664
      ],
      [
        1773741663307,
        12.779531363307486
      ],
      [
        1773745280304,
        12.778946628091399
      ],
      [
        1773749026205,
        12.778612351585133
      ],
      [
        1773752622132,
        12.778872232261216
      ],
      [
        1773763440878,
        97.20215313086321
      ],
      [
        1773767031689,
        97.20448347679944
      ],
      [
        1773770616604,
        97.20833167956415
      ],
      [
        1773774190503,
        97.20349202817906
      ],
      [
        1773777812294,
        97.20625202807632
      ],
      [
        1773781434104,
        97.20781109995787
      ],
      [
        1773784986250,
        97.20287949167466
      ],
      [
        1773788603538,
        97.20610912743089
      ],
      [
        1773792248618,
        97.2112123039023
      ],
      [
        1773810194040,
        84.43161175411079
      ],
      [
        1773813755494,
        84.4336544758675
      ],
      [
        1773817415039,
        84.42412320580839
      ],
      [
        1773820973480,
        84.42164875795392
      ],
      [
        1773824573243,
        84.42142841059339
      ],
      [
        1773828171810,
        84.42616153326843
      ],
      [
        1773831769522,
        84.42421946866153
      ],
      [
        1773835381234,
        84.4263377555495
      ],
      [
        1773838965449,
        84.42382767258377
      ],
      [
        1773871340730,
        2.8049871804178497
      ],
      [
        1773874930741,
        3.1986553836286546
      ],
      [
        1773878524851,
        3.1985286012253216
      ],
      [
        1773882132177,
        3.1986604327603225
      ],
      [
        1773885727338,
        3.1986787096748
      ],
      [
        1773889322471,
        3.198636189664882
      ],
      [
        1773892912246,
        3.1986611960741214
      ],
      [
        1773896535773,
        3.198521092242097
      ],
      [
        1773900114469,
        3.1984229391537973
      ],
      [
        1773903718815,
        3.1984184114270016
      ],
      [
        1774270980714,
        100.16640694590168
      ],
      [
        1774274580922,
        100.17975054265753
      ],
      [
        1774278157962,
        100.18747644504805
      ],
      [
        1774281754687,
        195.60762391181717
      ],
      [
        1774285402354,
        195.61005566882775
      ],
      [
        1774289005673,
        195.59417141463427
      ],
      [
        1774292601584,
        195.59197957247406
      ],
      [
        1774296199690,
        195.5970394531848
      ],
      [
        1774299805669,
        195.61005018764172
      ],
      [
        1774303398391,
        195.62500313542077
      ],
      [
        1774307000356,
        195.59444095312162
      ],
      [
        1774310606679,
        195.59769852476467
      ],
      [
        1774339301793,
        199.11249241989586
      ],
      [
        1774342901408,
        199.09202679422847
      ],
      [
        1774346501031,
        199.08931024770888
      ],
      [
        1774350106942,
        199.08101137896213
      ],
      [
        1774353694942,
        199.083671611533
      ],
      [
        1774357292144,
        98.92434479974568
      ],
      [
        1774360878102,
        98.93095549554498
      ],
      [
        1774364483296,
        98.90798044749441
      ],
      [
        1774368078822,
        96.92859082747857
      ],
      [
        1774371688418,
        1.499524209885035
      ],
      [
        1774375287880,
        1.4994301475230336
      ],
      [
        1774378893309,
        1.4993226961509316
      ],
      [
        1774382484977,
        1.499398069228892
      ],
      [
        1774386095431,
        1.4992448087574475
      ],
      [
        1774389690933,
        1.4991397966820945
      ],
      [
        1774393277988,
        1.499246319201256
      ],
      [
        1774396874944,
        1.4993190935763918
      ],
      [
        1774400475881,
        1.499385230286999
      ],
      [
        1774422077830,
        1.6778539048761454
      ],
      [
        1774425679267,
        1.6778005675154963
      ],
      [
        1774429288309,
        1.6777804942401782
      ],
      [
        1774432882662,
        1.6777804942401782
      ],
      [
        1774436411054,
        1.6777804942401782
      ],
      [
        1774440001942,
        1.6777804942401782
      ],
      [
        1774443616623,
        1.6777804942401782
      ],
      [
        1774447214291,
        1.6777804942401782
      ],
      [
        1774450818671,
        1.6777804942401782
      ],
      [
        1774587739636,
        2.212756375220115
      ],
      [
        1774591347021,
        2.2127166879002553
      ],
      [
        1774594948678,
        2.2127996836125936
      ],
      [
        1774598539534,
        2.2125801509043157
      ],
      [
        1774602150150,
        2.212779946791979
      ],
      [
        1774605732455,
        2.2127695313224787
      ],
      [
        1774609331177,
        2.212924628848894
      ],
      [
        1774612949977,
        2.2129815994586126
      ],
      [
        1774616530290,
        2.2130088269529313
      ],
      [
        1774663326317,
        0
      ],
      [
        1774666941582,
        0
      ],
      [
        1774670533476,
        0
      ],
      [
        1774674135510,
        0
      ],
      [
        1774677742628,
        0
      ],
      [
        1774681336553,
        0
      ],
      [
        1774684946051,
        0
      ],
      [
        1774688538961,
        0
      ],
      [
        1774692131902,
        0
      ],
      [
        1774706508865,
        3.2403869922086996
      ],
      [
        1774710115521,
        3.2402889218833932
      ],
      [
        1774713714116,
        3.2401970117725494
      ],
      [
        1774717313334,
        3.8609821018866084
      ],
      [
        1774720901045,
        3.8609990380275474
      ],
      [
        1774724510167,
        3.860930153488491
      ],
      [
        1774728119522,
        3.8610236463170264
      ],
      [
        1774731750884,
        3.9846626796788662
      ],
      [
        1774735345803,
        3.9846238691616858
      ],
      [
        1774738958900,
        3.9845762582482367
      ],
      [
        1774742554551,
        3.98474920995072
      ],
      [
        1774746147432,
        3.9850952712461374
      ],
      [
        1774749784718,
        3.9846397875951736
      ],
      [
        1774753447543,
        3.984632876956404
      ],
      [
        1774756989110,
        3.9846555383612055
      ],
      [
        1774760654845,
        3.984700976737557
      ],
      [
        1774767778608,
        2.0253750616866775
      ],
      [
        1774771422122,
        2.0253306888815645
      ],
      [
        1774774977959,
        2.0254015960685723
      ],
      [
        1774778570989,
        2.025361026590075
      ],
      [
        1774782164239,
        2.0254195061616964
      ],
      [
        1774785754993,
        2.0254356917018277
      ],
      [
        1774789387115,
        2.025399614345297
      ],
      [
        1774792978932,
        3.3911890727387357
      ],
      [
        1774796584632,
        2.7841491638949827
      ],
      [
        1774800172681,
        2.7841620888288277
      ],
      [
        1774803765392,
        2.163510555468018
      ],
      [
        1774807368997,
        2.1635789310397135
      ],
      [
        1774810953319,
        2.163544878620761
      ],
      [
        1774814555055,
        2.163616931714064
      ],
      [
        1774818158483,
        2.039529354931117
      ],
      [
        1774821770725,
        2.0395851720991316
      ],
      [
        1774825375954,
        2.0395783109835377
      ],
      [
        1774828959644,
        2.0396007704554453
      ],
      [
        1774832573147,
        2.039534507496337
      ],
      [
        1774836194812,
        2.0393516408877406
      ],
      [
        1774839735807,
        2.039409321585684
      ],
      [
        1774843341411,
        2.039281958705832
      ],
      [
        1774845190000,
        2.039362320807564
      ],
      [
        1774846923561,
        2.039362320807564
      ]
    ]
  }
}